Workbook

Sheet Data Menu
A1: APLIKASI PENELUSURAN MINAT KARIR HOLLAND RIASEC — VERSI FINAL 2026
A3: Data | B3: Isi
A4: Sekolah | B4: SMA Negeri Bengkulu
A5: Kelas | B5: XI . IPA. 1
A6: Tahun Pelajaran | B6: 2009/2010
A7: Tanggal Layanan | B7: 41365
A9: Sheet | B9: Fungsi
A10: Data Menu | B10: Informasi workbook, alur penggunaan, dan catatan pemutakhiran.
A11: Pertanyaan | B11: Lembar 216 pertanyaan yang telah dimodernisasi + 12 self-estimate.
A12: entri hasil dari isian siswa | B12: Identitas, jawaban item 1–216, 12 self-estimate, status data, pasangan dominan, dan tingkat konsistensi.
A13: Hasil Tes siswa | B13: Laporan individual: skor, kode 3 huruf, konsistensi, interpretasi, dan rekomendasi pekerjaan.
A14: Laporan Kelompok | B14: Ringkasan hasil seluruh siswa termasuk kode dan tingkat konsistensi.
A15: Hasil | B15: Perhitungan skor, peringkat, kode 3 huruf unik, rekomendasi, dan konsistensi.
A16: Kunci dari RIASEC | B16: 120 kombinasi kode tiga huruf dengan rekomendasi pekerjaan modern.
A17: Kunci Jawaban | B17: Pemetaan 216 item ke tipe RIASEC dan teks pernyataan versi pemutakhiran.
A19: ALUR PENGGUNAAN
A20: 1 | B20: Isi identitas sekolah/kelas pada bagian Data di atas.
A21: 2 | B21: Gunakan sheet “Pertanyaan” sebagai lembar soal/referensi saat pelaksanaan tes.
A22: 3 | B22: Masukkan identitas siswa pada sheet “entri hasil dari isian siswa”.
A23: 4 | B23: Item 1–216: masukkan 1 untuk setuju/dipilih; 0 atau kosong untuk tidak.
A24: 5 | B24: Isi seluruh 12 nilai Self Estimate (6 Pengetahuan + 6 Keterampilan), skala 1–7.
A25: 6 | B25: Pastikan Status Data = OK. Kode RIASEC, pasangan dominan, dan konsistensi akan terbentuk otomatis.
A26: 7 | B26: Pilih NIS/ID pada “Hasil Tes siswa” untuk laporan individual; gunakan “Laporan Kelompok” untuk rekap kelas.
A28: RUJUKAN PEMUTAKHIRAN | B28: O*NET Database 31.0 (Agustus 2026) dan O*NET OnLine Career Interest Types digunakan untuk memutakhirkan istilah/contoh pekerjaan.
A29: URL O*NET Database | B29: https://www.onetcenter.org/db_releases.html
A30: URL O*NET Interest Types | B30: https://www.onetonline.org/explore/interests/

Sheet entri hasil dari isian siswa
A1: ENTRI HASIL ISIAN SISWA — HOLLAND RIASEC
A2: PETUNJUK: Item 1–216 diisi 1 = setuju/dipilih; 0 atau kosong = tidak. SELF ESTIMATE wajib diisi lengkap untuk 6 tipe RIASEC pada PENGETAHUAN dan KETERAMPILAN dengan nilai 1–7. Setelah data lengkap, sistem membentuk kode RIASEC 3 huruf unik dan tingkat konsistensi berdasarkan dua huruf dominan. Kapasitas: 200 siswa.
A3: IDENTITAS | E3: AKTIVITAS — Item 1–66 | BS3: KEMAMPUAN/KETERAMPILAN — Item 67–132 | EG3: PEKERJAAN — Item 133–216 | HM3: SELF ESTIMATE — PENGETAHUAN | HS3: SELF ESTIMATE — KETERAMPILAN | HY3: KONTROL & KONSISTENSI
A4: No | B4: NIS / ID | C4: Nama Siswa | D4: L/P | E4: 1 | F4: 2 | G4: 3 | H4: 4 | I4: 5 | J4: 6 | K4: 7 | L4: 8 | M4: 9 | N4: 10 | O4: 11 | P4: 12 | Q4: 13 | R4: 14 | S4: 15 | T4: 16 | U4: 17 | V4: 18 | W4: 19 | X4: 20 | Y4: 21 | Z4: 22 | AA4: 23 | AB4: 24 | AC4: 25 | AD4: 26 | AE4: 27 | AF4: 28 | AG4: 29 | AH4: 30 | AI4: 31 | AJ4: 32 | AK4: 33 | AL4: 34 | AM4: 35 | AN4: 36 | AO4: 37 | AP4: 38 | AQ4: 39 | AR4: 40 | AS4: 41 | AT4: 42 | AU4: 43 | AV4: 44 | AW4: 45 | AX4: 46 | AY4: 47 | AZ4: 48 | BA4: 49 | BB4: 50 | BC4: 51 | BD4: 52 | BE4: 53 | BF4: 54 | BG4: 55 | BH4: 56 | BI4: 57 | BJ4: 58 | BK4: 59 | BL4: 60 | BM4: 61 | BN4: 62 | BO4: 63 | BP4: 64 | BQ4: 65 | BR4: 66 | BS4: 67 | BT4: 68 | BU4: 69 | BV4: 70 | BW4: 71 | BX4: 72 | BY4: 73 | BZ4: 74 | CA4: 75 | CB4: 76 | CC4: 77 | CD4: 78 | CE4: 79 | CF4: 80 | CG4: 81 | CH4: 82 | CI4: 83 | CJ4: 84 | CK4: 85 | CL4: 86 | CM4: 87 | CN4: 88 | CO4: 89 | CP4: 90 | CQ4: 91 | CR4: 92 | CS4: 93 | CT4: 94 | CU4: 95 | CV4: 96 | CW4: 97 | CX4: 98 | CY4: 99 | CZ4: 100 | DA4: 101 | DB4: 102 | DC4: 103 | DD4: 104 | DE4: 105 | DF4: 106 | DG4: 107 | DH4: 108 | DI4: 109 | DJ4: 110 | DK4: 111 | DL4: 112 | DM4: 113 | DN4: 114 | DO4: 115 | DP4: 116 | DQ4: 117 | DR4: 118 | DS4: 119 | DT4: 120 | DU4: 121 | DV4: 122 | DW4: 123 | DX4: 124 | DY4: 125 | DZ4: 126 | EA4: 127 | EB4: 128 | EC4: 129 | ED4: 130 | EE4: 131 | EF4: 132 | EG4: 133 | EH4: 134 | EI4: 135 | EJ4: 136 | EK4: 137 | EL4: 138 | EM4: 139 | EN4: 140 | EO4: 141 | EP4: 142 | EQ4: 143 | ER4: 144 | ES4: 145 | ET4: 146 | EU4: 147 | EV4: 148 | EW4: 149 | EX4: 150 | EY4: 151 | EZ4: 152 | FA4: 153 | FB4: 154 | FC4: 155 | FD4: 156 | FE4: 157 | FF4: 158 | FG4: 159 | FH4: 160 | FI4: 161 | FJ4: 162 | FK4: 163 | FL4: 164 | FM4: 165 | FN4: 166 | FO4: 167 | FP4: 168 | FQ4: 169 | FR4: 170 | FS4: 171 | FT4: 172 | FU4: 173 | FV4: 174 | FW4: 175 | FX4: 176 | FY4: 177 | FZ4: 178 | GA4: 179 | GB4: 180 | GC4: 181 | GD4: 182 | GE4: 183 | GF4: 184 | GG4: 185 | GH4: 186 | GI4: 187 | GJ4: 188 | GK4: 189 | GL4: 190 | GM4: 191 | GN4: 192 | GO4: 193 | GP4: 194 | GQ4: 195 | GR4: 196 | GS4: 197 | GT4: 198 | GU4: 199 | GV4: 200 | GW4: 201 | GX4: 202 | GY4: 203 | GZ4: 204 | HA4: 205 | HB4: 206 | HC4: 207 | HD4: 208 | HE4: 209 | HF4: 210 | HG4: 211 | HH4: 212 | HI4: 213 | HJ4: 214 | HK4: 215 | HL4: 216 | HM4: R | HN4: I | HO4: A | HP4: S | HQ4: E | HR4: C | HS4: R | HT4: I | HU4: A | HV4: S | HW4: E | HX4: C | HY4: Status Data | HZ4: Pasangan Dominan | IA4: Tingkat Konsistensi
A5: 1 | B5: 22001 | C5: Selly Aljannah | D5: L | E5: 1 | F5: 1 | G5: 1 | H5: 1 | K5: 1 | M5: 1 | O5: 1 | BS5: 1 | BT5: 1 | BU5: 1 | BV5: 1 | BY5: 1 | CA5: 1 | CC5: 1 | EG5: 1 | EH5: 1 | EI5: 1 | EJ5: 1 | EM5: 1 | EO5: 1 | EQ5: 1 | HM5: 3 | HN5: 2 | HO5: 4 | HP5: 5 | HQ5: 3 | HR5: 6 | HS5: 3 | HT5: 2 | HU5: 4 | HV5: 5 | HW5: 3 | HX5: 6 | HY5: =IF(AND(B5="",C5=""),"",IF(OR(B5="",C5=""),"Lengkapi identitas",IF(COUNT(HM5:HX5)<12,"Lengkapi 12 Self Estimate",IF(OR(MIN(HM5:HX5)<1,MAX(HM5:HX5)>7),"Self Estimate harus 1–7","OK")))) -> OK | HZ5: =IF($HY5<>"OK","",Hasil!$AU5) -> RC | IA5: =IF($HY5<>"OK","",Hasil!$AV5) -> Tinggi
A6: 2 | B6: 22002 | C6: Siti Solekha | D6: L | E6: 1 | F6: 1 | G6: 1 | H6: 1 | K6: 1 | M6: 1 | O6: 1 | BS6: 1 | BT6: 1 | BU6: 1 | BV6: 1 | BY6: 1 | CA6: 1 | CC6: 1 | EG6: 1 | EH6: 1 | EI6: 1 | EJ6: 1 | EM6: 1 | EO6: 1 | EQ6: 1 | HM6: 3 | HN6: 2 | HO6: 4 | HP6: 5 | HQ6: 3 | HR6: 6 | HS6: 3 | HT6: 2 | HU6: 4 | HV6: 5 | HW6: 3 | HX6: 6 | HY6: =IF(AND(B6="",C6=""),"",IF(OR(B6="",C6=""),"Lengkapi identitas",IF(COUNT(HM6:HX6)<12,"Lengkapi 12 Self Estimate",IF(OR(MIN(HM6:HX6)<1,MAX(HM6:HX6)>7),"Self Estimate harus 1–7","OK")))) -> OK | HZ6: =IF($HY6<>"OK","",Hasil!$AU6) -> RC | IA6: =IF($HY6<>"OK","",Hasil!$AV6) -> Tinggi
A7: 3 | B7: 22003 | C7: Sri Panca Lestari | D7: L | E7: 1 | F7: 1 | G7: 1 | H7: 1 | K7: 1 | M7: 1 | O7: 1 | BS7: 1 | BT7: 1 | BU7: 1 | BV7: 1 | BY7: 1 | CA7: 1 | CC7: 1 | EG7: 1 | EH7: 1 | EI7: 1 | EJ7: 1 | EM7: 1 | EO7: 1 | EQ7: 1 | HM7: 3 | HN7: 2 | HO7: 4 | HP7: 5 | HQ7: 3 | HR7: 6 | HS7: 3 | HT7: 2 | HU7: 4 | HV7: 5 | HW7: 3 | HX7: 6 | HY7: =IF(AND(B7="",C7=""),"",IF(OR(B7="",C7=""),"Lengkapi identitas",IF(COUNT(HM7:HX7)<12,"Lengkapi 12 Self Estimate",IF(OR(MIN(HM7:HX7)<1,MAX(HM7:HX7)>7),"Self Estimate harus 1–7","OK")))) -> OK | HZ7: =IF($HY7<>"OK","",Hasil!$AU7) -> RC | IA7: =IF($HY7<>"OK","",Hasil!$AV7) -> Tinggi
A8: 4 | B8: 22004 | C8: Widi Hartanto | D8: L | E8: 1 | F8: 1 | G8: 1 | H8: 1 | K8: 1 | M8: 1 | O8: 1 | BS8: 1 | BT8: 1 | BU8: 1 | BV8: 1 | BY8: 1 | CA8: 1 | CC8: 1 | EG8: 1 | EH8: 1 | EI8: 1 | EJ8: 1 | EM8: 1 | EO8: 1 | EQ8: 1 | HM8: 3 | HN8: 2 | HO8: 4 | HP8: 5 | HQ8: 3 | HR8: 6 | HS8: 3 | HT8: 2 | HU8: 4 | HV8: 5 | HW8: 3 | HX8: 6 | HY8: =IF(AND(B8="",C8=""),"",IF(OR(B8="",C8=""),"Lengkapi identitas",IF(COUNT(HM8:HX8)<12,"Lengkapi 12 Self Estimate",IF(OR(MIN(HM8:HX8)<1,MAX(HM8:HX8)>7),"Self Estimate harus 1–7","OK")))) -> OK | HZ8: =IF($HY8<>"OK","",Hasil!$AU8) -> RC | IA8: =IF($HY8<>"OK","",Hasil!$AV8) -> Tinggi
A9: 5 | B9: 22005 | C9: Puji Lestari | D9: L | E9: 1 | F9: 1 | G9: 1 | H9: 1 | K9: 1 | M9: 1 | O9: 1 | BS9: 1 | BT9: 1 | BU9: 1 | BV9: 1 | BY9: 1 | CA9: 1 | CC9: 1 | EG9: 1 | EH9: 1 | EI9: 1 | EJ9: 1 | EM9: 1 | EO9: 1 | EQ9: 1 | HM9: 3 | HN9: 2 | HO9: 4 | HP9: 5 | HQ9: 3 | HR9: 6 | HS9: 3 | HT9: 2 | HU9: 4 | HV9: 5 | HW9: 3 | HX9: 6 | HY9: =IF(AND(B9="",C9=""),"",IF(OR(B9="",C9=""),"Lengkapi identitas",IF(COUNT(HM9:HX9)<12,"Lengkapi 12 Self Estimate",IF(OR(MIN(HM9:HX9)<1,MAX(HM9:HX9)>7),"Self Estimate harus 1–7","OK")))) -> OK | HZ9: =IF($HY9<>"OK","",Hasil!$AU9) -> RC | IA9: =IF($HY9<>"OK","",Hasil!$AV9) -> Tinggi
A10: 6 | B10: 22006 | C10: Silvia Noviana N | D10: L | E10: 1 | F10: 1 | G10: 1 | H10: 1 | K10: 1 | M10: 1 | O10: 1 | BS10: 1 | BT10: 1 | BU10: 1 | BV10: 1 | BY10: 1 | CA10: 1 | CC10: 1 | EG10: 1 | EH10: 1 | EI10: 1 | EJ10: 1 | EM10: 1 | EO10: 1 | EQ10: 1 | HM10: 3 | HN10: 2 | HO10: 4 | HP10: 5 | HQ10: 3 | HR10: 6 | HS10: 3 | HT10: 2 | HU10: 4 | HV10: 5 | HW10: 3 | HX10: 6 | HY10: =IF(AND(B10="",C10=""),"",IF(OR(B10="",C10=""),"Lengkapi identitas",IF(COUNT(HM10:HX10)<12,"Lengkapi 12 Self Estimate",IF(OR(MIN(HM10:HX10)<1,MAX(HM10:HX10)>7),"Self Estimate harus 1–7","OK")))) -> OK | HZ10: =IF($HY10<>"OK","",Hasil!$AU10) -> RC | IA10: =IF($HY10<>"OK","",Hasil!$AV10) -> Tinggi
A11: 7 | B11: 22007 | C11: Sinta Intani Fitriana | D11: L | E11: 1 | F11: 1 | G11: 1 | H11: 1 | K11: 1 | M11: 1 | O11: 1 | BS11: 1 | BT11: 1 | BU11: 1 | BV11: 1 | BY11: 1 | CA11: 1 | CC11: 1 | EG11: 1 | EH11: 1 | EI11: 1 | EJ11: 1 | EM11: 1 | EO11: 1 | EQ11: 1 | HM11: 3 | HN11: 2 | HO11: 4 | HP11: 5 | HQ11: 3 | HR11: 6 | HS11: 3 | HT11: 2 | HU11: 4 | HV11: 5 | HW11: 3 | HX11: 6 | HY11: =IF(AND(B11="",C11=""),"",IF(OR(B11="",C11=""),"Lengkapi identitas",IF(COUNT(HM11:HX11)<12,"Lengkapi 12 Self Estimate",IF(OR(MIN(HM11:HX11)<1,MAX(HM11:HX11)>7),"Self Estimate harus 1–7","OK")))) -> OK | HZ11: =IF($HY11<>"OK","",Hasil!$AU11) -> RC | IA11: =IF($HY11<>"OK","",Hasil!$AV11) -> Tinggi
A12: 8 | B12: 22008 | C12: Siti Nur Fadhilah | D12: L | E12: 1 | K12: 1 | M12: 1 | O12: 1 | HY12: =IF(AND(B12="",C12=""),"",IF(OR(B12="",C12=""),"Lengkapi identitas",IF(COUNT(HM12:HX12)<12,"Lengkapi 12 Self Estimate",IF(OR(MIN(HM12:HX12)<1,MAX(HM12:HX12)>7),"Self Estimate harus 1–7","OK")))) -> Lengkapi 12 Self Estimate | HZ12: =IF($HY12<>"OK","",Hasil!$AU12) | IA12: =IF($HY12<>"OK","",Hasil!$AV12)
A13: 9 | B13: 22009 | C13: Khotimatuz Zuhriyah | D13: L | E13: 1 | K13: 1 | M13: 1 | O13: 1 | HY13: =IF(AND(B13="",C13=""),"",IF(OR(B13="",C13=""),"Lengkapi identitas",IF(COUNT(HM13:HX13)<12,"Lengkapi 12 Self Estimate",IF(OR(MIN(HM13:HX13)<1,MAX(HM13:HX13)>7),"Self Estimate harus 1–7","OK")))) -> Lengkapi 12 Self Estimate | HZ13: =IF($HY13<>"OK","",Hasil!$AU13) | IA13: =IF($HY13<>"OK","",Hasil!$AV13)
A14: 10 | B14: 22010 | C14: Kukuh Priyatin | D14: L | E14: 1 | K14: 1 | M14: 1 | O14: 1 | HY14: =IF(AND(B14="",C14=""),"",IF(OR(B14="",C14=""),"Lengkapi identitas",IF(COUNT(HM14:HX14)<12,"Lengkapi 12 Self Estimate",IF(OR(MIN(HM14:HX14)<1,MAX(HM14:HX14)>7),"Self Estimate harus 1–7","OK")))) -> Lengkapi 12 Self Estimate | HZ14: =IF($HY14<>"OK","",Hasil!$AU14) | IA14: =IF($HY14<>"OK","",Hasil!$AV14)
A15: 11 | B15: 22011 | C15: Mas Karebet Setiawan | D15: L | E15: 1 | K15: 1 | M15: 1 | O15: 1 | HY15: =IF(AND(B15="",C15=""),"",IF(OR(B15="",C15=""),"Lengkapi identitas",IF(COUNT(HM15:HX15)<12,"Lengkapi 12 Self Estimate",IF(OR(MIN(HM15:HX15)<1,MAX(HM15:HX15)>7),"Self Estimate harus 1–7","OK")))) -> Lengkapi 12 Self Estimate | HZ15: =IF($HY15<>"OK","",Hasil!$AU15) | IA15: =IF($HY15<>"OK","",Hasil!$AV15)
A16: 12 | B16: 22012 | C16: Mauidhotul Hasanah Ismail | D16: L | E16: 1 | K16: 1 | M16: 1 | O16: 1 | HY16: =IF(AND(B16="",C16=""),"",IF(OR(B16="",C16=""),"Lengkapi identitas",IF(COUNT(HM16:HX16)<12,"Lengkapi 12 Self Estimate",IF(OR(MIN(HM16:HX16)<1,MAX(HM16:HX16)>7),"Self Estimate harus 1–7","OK")))) -> Lengkapi 12 Self Estimate | HZ16: =IF($HY16<>"OK","",Hasil!$AU16) | IA16: =IF($HY16<>"OK","",Hasil!$AV16)
A17: 13 | B17: 22013 | C17: Ririn Fauziyah | D17: L | E17: 1 | K17: 1 | M17: 1 | O17: 1 | HY17: =IF(AND(B17="",C17=""),"",IF(OR(B17="",C17=""),"Lengkapi identitas",IF(COUNT(HM17:HX17)<12,"Lengkapi 12 Self Estimate",IF(OR(MIN(HM17:HX17)<1,MAX(HM17:HX17)>7),"Self Estimate harus 1–7","OK")))) -> Lengkapi 12 Self Estimate | HZ17: =IF($HY17<>"OK","",Hasil!$AU17) | IA17: =IF($HY17<>"OK","",Hasil!$AV17)
A18: 14 | B18: 22014 | C18: Ulfatul Maula | D18: L | HY18: =IF(AND(B18="",C18=""),"",IF(OR(B18="",C18=""),"Lengkapi identitas",IF(COUNT(HM18:HX18)<12,"Lengkapi 12 Self Estimate",IF(OR(MIN(HM18:HX18)<1,MAX(HM18:HX18)>7),"Self Estimate harus 1–7","OK")))) -> Lengkapi 12 Self Estimate | HZ18: =IF($HY18<>"OK","",Hasil!$AU18) | IA18: =IF($HY18<>"OK","",Hasil!$AV18)
A19: 15 | B19: 22015 | C19: Rizki Imam Fauzi | D19: L | HY19: =IF(AND(B19="",C19=""),"",IF(OR(B19="",C19=""),"Lengkapi identitas",IF(COUNT(HM19:HX19)<12,"Lengkapi 12 Self Estimate",IF(OR(MIN(HM19:HX19)<1,MAX(HM19:HX19)>7),"Self Estimate harus 1–7","OK")))) -> Lengkapi 12 Self Estimate | HZ19: =IF($HY19<>"OK","",Hasil!$AU19) | IA19: =IF($HY19<>"OK","",Hasil!$AV19)
A20: 16 | B20: 22016 | C20: Siti Arisah | D20: L | HY20: =IF(AND(B20="",C20=""),"",IF(OR(B20="",C20=""),"Lengkapi identitas",IF(COUNT(HM20:HX20)<12,"Lengkapi 12 Self Estimate",IF(OR(MIN(HM20:HX20)<1,MAX(HM20:HX20)>7),"Self Estimate harus 1–7","OK")))) -> Lengkapi 12 Self Estimate | HZ20: =IF($HY20<>"OK","",Hasil!$AU20) | IA20: =IF($HY20<>"OK","",Hasil!$AV20)
A21: 17 | B21: 22017 | C21: Slamet Riyadi | D21: L | HY21: =IF(AND(B21="",C21=""),"",IF(OR(B21="",C21=""),"Lengkapi identitas",IF(COUNT(HM21:HX21)<12,"Lengkapi 12 Self Estimate",IF(OR(MIN(HM21:HX21)<1,MAX(HM21:HX21)>7),"Self Estimate harus 1–7","OK")))) -> Lengkapi 12 Self Estimate | HZ21: =IF($HY21<>"OK","",Hasil!$AU21) | IA21: =IF($HY21<>"OK","",Hasil!$AV21)
A22: 18 | B22: 22018 | C22: Sri Harnita | D22: L | HY22: =IF(AND(B22="",C22=""),"",IF(OR(B22="",C22=""),"Lengkapi identitas",IF(COUNT(HM22:HX22)<12,"Lengkapi 12 Self Estimate",IF(OR(MIN(HM22:HX22)<1,MAX(HM22:HX22)>7),"Self Estimate harus 1–7","OK")))) -> Lengkapi 12 Self Estimate | HZ22: =IF($HY22<>"OK","",Hasil!$AU22) | IA22: =IF($HY22<>"OK","",Hasil!$AV22)
A23: 19 | B23: 22019 | C23: Tentri Year Itqa Retma N | D23: L | HY23: =IF(AND(B23="",C23=""),"",IF(OR(B23="",C23=""),"Lengkapi identitas",IF(COUNT(HM23:HX23)<12,"Lengkapi 12 Self Estimate",IF(OR(MIN(HM23:HX23)<1,MAX(HM23:HX23)>7),"Self Estimate harus 1–7","OK")))) -> Lengkapi 12 Self Estimate | HZ23: =IF($HY23<>"OK","",Hasil!$AU23) | IA23: =IF($HY23<>"OK","",Hasil!$AV23)
A24: 20 | B24: 22020 | C24: Winda Andriyani | D24: L | HY24: =IF(AND(B24="",C24=""),"",IF(OR(B24="",C24=""),"Lengkapi identitas",IF(COUNT(HM24:HX24)<12,"Lengkapi 12 Self Estimate",IF(OR(MIN(HM24:HX24)<1,MAX(HM24:HX24)>7),"Self Estimate harus 1–7","OK")))) -> Lengkapi 12 Self Estimate | HZ24: =IF($HY24<>"OK","",Hasil!$AU24) | IA24: =IF($HY24<>"OK","",Hasil!$AV24)
A25: 21 | B25: 22021 | C25: Hasan Agus Salim | D25: L | HY25: =IF(AND(B25="",C25=""),"",IF(OR(B25="",C25=""),"Lengkapi identitas",IF(COUNT(HM25:HX25)<12,"Lengkapi 12 Self Estimate",IF(OR(MIN(HM25:HX25)<1,MAX(HM25:HX25)>7),"Self Estimate harus 1–7","OK")))) -> Lengkapi 12 Self Estimate | HZ25: =IF($HY25<>"OK","",Hasil!$AU25) | IA25: =IF($HY25<>"OK","",Hasil!$AV25)
A26: 22 | B26: 22022 | C26: Muhammad Tondi Prasetyo | D26: L | HY26: =IF(AND(B26="",C26=""),"",IF(OR(B26="",C26=""),"Lengkapi identitas",IF(COUNT(HM26:HX26)<12,"Lengkapi 12 Self Estimate",IF(OR(MIN(HM26:HX26)<1,MAX(HM26:HX26)>7),"Self Estimate harus 1–7","OK")))) -> Lengkapi 12 Self Estimate | HZ26: =IF($HY26<>"OK","",Hasil!$AU26) | IA26: =IF($HY26<>"OK","",Hasil!$AV26)
A27: 23 | B27: 22023 | C27: Raudatul Jannah | D27: L | HY27: =IF(AND(B27="",C27=""),"",IF(OR(B27="",C27=""),"Lengkapi identitas",IF(COUNT(HM27:HX27)<12,"Lengkapi 12 Self Estimate",IF(OR(MIN(HM27:HX27)<1,MAX(HM27:HX27)>7),"Self Estimate harus 1–7","OK")))) -> Lengkapi 12 Self Estimate | HZ27: =IF($HY27<>"OK","",Hasil!$AU27) | IA27: =IF($HY27<>"OK","",Hasil!$AV27)
A28: 24 | B28: 22024 | C28: Titi Larasati | D28: L | HY28: =IF(AND(B28="",C28=""),"",IF(OR(B28="",C28=""),"Lengkapi identitas",IF(COUNT(HM28:HX28)<12,"Lengkapi 12 Self Estimate",IF(OR(MIN(HM28:HX28)<1,MAX(HM28:HX28)>7),"Self Estimate harus 1–7","OK")))) -> Lengkapi 12 Self Estimate | HZ28: =IF($HY28<>"OK","",Hasil!$AU28) | IA28: =IF($HY28<>"OK","",Hasil!$AV28)
A29: 25 | B29: 22025 | C29: Tri Purwaningsih | D29: L | HY29: =IF(AND(B29="",C29=""),"",IF(OR(B29="",C29=""),"Lengkapi identitas",IF(COUNT(HM29:HX29)<12,"Lengkapi 12 Self Estimate",IF(OR(MIN(HM29:HX29)<1,MAX(HM29:HX29)>7),"Self Estimate harus 1–7","OK")))) -> Lengkapi 12 Self Estimate | HZ29: =IF($HY29<>"OK","",Hasil!$AU29) | IA29: =IF($HY29<>"OK","",Hasil!$AV29)
... A41: 37 | B41: 22037 | C41: Yuli Aji Yakup | D41: L | HY41: =IF(AND(B41="",C41=""),"",IF(OR(B41="",C41=""),"Lengkapi identitas",IF(COUNT(HM41:HX41)<12,"Lengkapi 12 Self Estimate",IF(OR(MIN(HM41:HX41)<1,MAX(HM41:HX41)>7),"Self Estimate harus 1–7","OK")))) -> Lengkapi 12 Self Estimate | HZ41: =IF($HY41<>"OK","",Hasil!$AU41) | IA41: =IF($HY41<>"OK","",Hasil!$AV41)
A42: 38 | HY42: =IF(AND(B42="",C42=""),"",IF(OR(B42="",C42=""),"Lengkapi identitas",IF(COUNT(HM42:HX42)<12,"Lengkapi 12 Self Estimate",IF(OR(MIN(HM42:HX42)<1,MAX(HM42:HX42)>7),"Self Estimate harus 1–7","OK")))) | HZ42: =IF($HY42<>"OK","",Hasil!$AU42) | IA42: =IF($HY42<>"OK","",Hasil!$AV42)
A43: 39 | HY43: =IF(AND(B43="",C43=""),"",IF(OR(B43="",C43=""),"Lengkapi identitas",IF(COUNT(HM43:HX43)<12,"Lengkapi 12 Self Estimate",IF(OR(MIN(HM43:HX43)<1,MAX(HM43:HX43)>7),"Self Estimate harus 1–7","OK")))) | HZ43: =IF($HY43<>"OK","",Hasil!$AU43) | IA43: =IF($HY43<>"OK","",Hasil!$AV43)
A44: 40 | HY44: =IF(AND(B44="",C44=""),"",IF(OR(B44="",C44=""),"Lengkapi identitas",IF(COUNT(HM44:HX44)<12,"Lengkapi 12 Self Estimate",IF(OR(MIN(HM44:HX44)<1,MAX(HM44:HX44)>7),"Self Estimate harus 1–7","OK")))) | HZ44: =IF($HY44<>"OK","",Hasil!$AU44) | IA44: =IF($HY44<>"OK","",Hasil!$AV44)
A45: 41 | HY45: =IF(AND(B45="",C45=""),"",IF(OR(B45="",C45=""),"Lengkapi identitas",IF(COUNT(HM45:HX45)<12,"Lengkapi 12 Self Estimate",IF(OR(MIN(HM45:HX45)<1,MAX(HM45:HX45)>7),"Self Estimate harus 1–7","OK")))) | HZ45: =IF($HY45<>"OK","",Hasil!$AU45) | IA45: =IF($HY45<>"OK","",Hasil!$AV45)
A46: 42 | HY46: =IF(AND(B46="",C46=""),"",IF(OR(B46="",C46=""),"Lengkapi identitas",IF(COUNT(HM46:HX46)<12,"Lengkapi 12 Self Estimate",IF(OR(MIN(HM46:HX46)<1,MAX(HM46:HX46)>7),"Self Estimate harus 1–7","OK")))) | HZ46: =IF($HY46<>"OK","",Hasil!$AU46) | IA46: =IF($HY46<>"OK","",Hasil!$AV46)
A47: 43 | HY47: =IF(AND(B47="",C47=""),"",IF(OR(B47="",C47=""),"Lengkapi identitas",IF(COUNT(HM47:HX47)<12,"Lengkapi 12 Self Estimate",IF(OR(MIN(HM47:HX47)<1,MAX(HM47:HX47)>7),"Self Estimate harus 1–7","OK")))) | HZ47: =IF($HY47<>"OK","",Hasil!$AU47) | IA47: =IF($HY47<>"OK","",Hasil!$AV47)
A48: 44 | HY48: =IF(AND(B48="",C48=""),"",IF(OR(B48="",C48=""),"Lengkapi identitas",IF(COUNT(HM48:HX48)<12,"Lengkapi 12 Self Estimate",IF(OR(MIN(HM48:HX48)<1,MAX(HM48:HX48)>7),"Self Estimate harus 1–7","OK")))) | HZ48: =IF($HY48<>"OK","",Hasil!$AU48) | IA48: =IF($HY48<>"OK","",Hasil!$AV48)
A49: 45 | HY49: =IF(AND(B49="",C49=""),"",IF(OR(B49="",C49=""),"Lengkapi identitas",IF(COUNT(HM49:HX49)<12,"Lengkapi 12 Self Estimate",IF(OR(MIN(HM49:HX49)<1,MAX(HM49:HX49)>7),"Self Estimate harus 1–7","OK")))) | HZ49: =IF($HY49<>"OK","",Hasil!$AU49) | IA49: =IF($HY49<>"OK","",Hasil!$AV49)
A50: 46 | HY50: =IF(AND(B50="",C50=""),"",IF(OR(B50="",C50=""),"Lengkapi identitas",IF(COUNT(HM50:HX50)<12,"Lengkapi 12 Self Estimate",IF(OR(MIN(HM50:HX50)<1,MAX(HM50:HX50)>7),"Self Estimate harus 1–7","OK")))) | HZ50: =IF($HY50<>"OK","",Hasil!$AU50) | IA50: =IF($HY50<>"OK","",Hasil!$AV50)
A51: 47 | HY51: =IF(AND(B51="",C51=""),"",IF(OR(B51="",C51=""),"Lengkapi identitas",IF(COUNT(HM51:HX51)<12,"Lengkapi 12 Self Estimate",IF(OR(MIN(HM51:HX51)<1,MAX(HM51:HX51)>7),"Self Estimate harus 1–7","OK")))) | HZ51: =IF($HY51<>"OK","",Hasil!$AU51) | IA51: =IF($HY51<>"OK","",Hasil!$AV51)
A52: 48 | HY52: =IF(AND(B52="",C52=""),"",IF(OR(B52="",C52=""),"Lengkapi identitas",IF(COUNT(HM52:HX52)<12,"Lengkapi 12 Self Estimate",IF(OR(MIN(HM52:HX52)<1,MAX(HM52:HX52)>7),"Self Estimate harus 1–7","OK")))) | HZ52: =IF($HY52<>"OK","",Hasil!$AU52) | IA52: =IF($HY52<>"OK","",Hasil!$AV52)
A53: 49 | HY53: =IF(AND(B53="",C53=""),"",IF(OR(B53="",C53=""),"Lengkapi identitas",IF(COUNT(HM53:HX53)<12,"Lengkapi 12 Self Estimate",IF(OR(MIN(HM53:HX53)<1,MAX(HM53:HX53)>7),"Self Estimate harus 1–7","OK")))) | HZ53: =IF($HY53<>"OK","",Hasil!$AU53) | IA53: =IF($HY53<>"OK","",Hasil!$AV53)
... A204: 200 | HY204: =IF(AND(B204="",C204=""),"",IF(OR(B204="",C204=""),"Lengkapi identitas",IF(COUNT(HM204:HX204)<12,"Lengkapi 12 Self Estimate",IF(OR(MIN(HM204:HX204)<1,MAX(HM204:HX204)>7),"Self Estimate harus 1–7","OK")))) | HZ204: =IF($HY204<>"OK","",Hasil!$AU204) | IA204: =IF($HY204<>"OK","",Hasil!$AV204)

Sheet Hasil Tes siswa
A1: HASIL TES SISWA — HOLLAND RIASEC
A3: NIS / ID Siswa | B3: 22004 | D3: Status Data | E3: =IFERROR(INDEX(Hasil!$V$5:$V$204,MATCH($B$3,Hasil!$B$5:$B$204,0)),"Pilih NIS/ID") -> OK
A4: Pasangan Dominan | B4: =IFERROR(INDEX(Hasil!$AU$5:$AU$204,MATCH($B$3,Hasil!$B$5:$B$204,0)),"") -> RC | D4: Tingkat Konsistensi | E4: =IFERROR(INDEX(Hasil!$AV$5:$AV$204,MATCH($B$3,Hasil!$B$5:$B$204,0)),"") -> Tinggi
A5: Nama | B5: =IFERROR(INDEX(Hasil!$C$5:$C$204,MATCH($B$3,Hasil!$B$5:$B$204,0)),"") -> Widi Hartanto
A6: Jenis Kelamin | B6: =IFERROR(INDEX(Hasil!$D$5:$D$204,MATCH($B$3,Hasil!$B$5:$B$204,0)),"") -> L
A7: Kode RIASEC | B7: =IFERROR(INDEX(Hasil!$T$5:$T$204,MATCH($B$3,Hasil!$B$5:$B$204,0)),"") -> RCS
A8: Rekomendasi Karier | B8: =IFERROR(INDEX(Hasil!$U$5:$U$204,MATCH($B$3,Hasil!$B$5:$B$204,0)),"") -> Teknisi quality control; Programmer/operator CNC; Teknisi kalibrasi; Maintenance planner; Production planner; Koordinator layanan teknis terjadwal; Petugas kontrol alat kesehatan; Koordinator operasional bengkel layanan; Teknisi smart manufacturing; Maintenance planning specialist; Ship officer / captain; QA/QC technician; Koordinator otomasi gudang
A10: Tipe | B10: Skor | C10: Peringkat | D10: Posisi
A11: R | B11: =IFERROR(INDEX(Hasil!$E$5:$J$204,MATCH($B$3,Hasil!$B$5:$B$204,0),1),"") -> 27 | C11: =IFERROR(INDEX(Hasil!$K$5:$P$204,MATCH($B$3,Hasil!$B$5:$B$204,0),1),"") -> 1 | D11: =IF(C11="","",IF(C11=1,"Dominan 1",IF(C11=2,"Dominan 2",IF(C11=3,"Dominan 3","")))) -> Dominan 1
A12: I | B12: =IFERROR(INDEX(Hasil!$E$5:$J$204,MATCH($B$3,Hasil!$B$5:$B$204,0),2),"") -> 4 | C12: =IFERROR(INDEX(Hasil!$K$5:$P$204,MATCH($B$3,Hasil!$B$5:$B$204,0),2),"") -> 6 | D12: =IF(C12="","",IF(C12=1,"Dominan 1",IF(C12=2,"Dominan 2",IF(C12=3,"Dominan 3",""))))
A13: A | B13: =IFERROR(INDEX(Hasil!$E$5:$J$204,MATCH($B$3,Hasil!$B$5:$B$204,0),3),"") -> 8 | C13: =IFERROR(INDEX(Hasil!$K$5:$P$204,MATCH($B$3,Hasil!$B$5:$B$204,0),3),"") -> 4 | D13: =IF(C13="","",IF(C13=1,"Dominan 1",IF(C13=2,"Dominan 2",IF(C13=3,"Dominan 3",""))))
A14: S | B14: =IFERROR(INDEX(Hasil!$E$5:$J$204,MATCH($B$3,Hasil!$B$5:$B$204,0),4),"") -> 10 | C14: =IFERROR(INDEX(Hasil!$K$5:$P$204,MATCH($B$3,Hasil!$B$5:$B$204,0),4),"") -> 3 | D14: =IF(C14="","",IF(C14=1,"Dominan 1",IF(C14=2,"Dominan 2",IF(C14=3,"Dominan 3","")))) -> Dominan 3
A15: E | B15: =IFERROR(INDEX(Hasil!$E$5:$J$204,MATCH($B$3,Hasil!$B$5:$B$204,0),5),"") -> 6 | C15: =IFERROR(INDEX(Hasil!$K$5:$P$204,MATCH($B$3,Hasil!$B$5:$B$204,0),5),"") -> 5 | D15: =IF(C15="","",IF(C15=1,"Dominan 1",IF(C15=2,"Dominan 2",IF(C15=3,"Dominan 3",""))))
A16: C | B16: =IFERROR(INDEX(Hasil!$E$5:$J$204,MATCH($B$3,Hasil!$B$5:$B$204,0),6),"") -> 12 | C16: =IFERROR(INDEX(Hasil!$K$5:$P$204,MATCH($B$3,Hasil!$B$5:$B$204,0),6),"") -> 2 | D16: =IF(C16="","",IF(C16=1,"Dominan 1",IF(C16=2,"Dominan 2",IF(C16=3,"Dominan 3","")))) -> Dominan 2
A18: INTERPRETASI TIGA TIPE TERATAS
A20: Dominan 1 | B20: =IF($B$7="","",MID($B$7,1,1)) -> R
A21: Karakteristik | B21: =IFERROR(VLOOKUP($B$20,'Kunci dari RIASEC'!$E$4:$H$9,3,FALSE),"") -> Menyukai aktivitas praktis dan langsung, bekerja dengan alat, mesin, teknologi, material, hewan, atau lingkungan fisik. Cenderung nyaman dengan pemecahan masalah konkret, aktivitas lapangan, dan hasil kerja yang dapat diamati.
A22: Jurusan yang relevan | B22: =IFERROR(VLOOKUP($B$20,'Kunci dari RIASEC'!$E$4:$H$9,4,FALSE),"") -> Teknik Mesin, Teknik Elektro, Teknik Sipil, Mekatronika, Teknik Otomotif, Teknik Energi/Energi Terbarukan, Geomatika, Pertanian, Perikanan, Kehutanan, Teknik Industri.
A24: Dominan 2 | B24: =IF($B$7="","",MID($B$7,2,1)) -> C
A25: Karakteristik | B25: =IFERROR(VLOOKUP($B$24,'Kunci dari RIASEC'!$E$4:$H$9,3,FALSE),"") -> Menyukai aktivitas yang terstruktur, teratur, teliti, sistematis, dan berbasis prosedur, data, angka, dokumen, serta pengelolaan informasi. Cenderung nyaman dengan aturan yang jelas, ketepatan, pencatatan, dan standar kerja yang konsisten.
A26: Jurusan yang relevan | B26: =IFERROR(VLOOKUP($B$24,'Kunci dari RIASEC'!$E$4:$H$9,4,FALSE),"") -> Akuntansi, Perpajakan, Keuangan, Administrasi Bisnis, Administrasi Perkantoran, Sistem Informasi, Manajemen Data, Audit, Perbankan, Manajemen Rantai Pasok, Manajemen Operasi, Kearsipan dan Manajemen Dokumen.
A28: Dominan 3 | B28: =IF($B$7="","",MID($B$7,3,1)) -> S
A29: Karakteristik | B29: =IFERROR(VLOOKUP($B$28,'Kunci dari RIASEC'!$E$4:$H$9,3,FALSE),"") -> Menyukai aktivitas membantu, mengajar, membimbing, merawat, mendampingi, berkomunikasi, dan bekerja bersama orang lain. Cenderung memperoleh kepuasan dari perkembangan, pembelajaran, kesehatan, dan kesejahteraan individu atau komunitas.
A30: Jurusan yang relevan | B30: =IFERROR(VLOOKUP($B$28,'Kunci dari RIASEC'!$E$4:$H$9,4,FALSE),"") -> Pendidikan, Bimbingan dan Konseling, Psikologi, Keperawatan, Kesehatan Masyarakat, Pekerjaan Sosial, Pendidikan Khusus, Terapi/Rehabilitasi, Pengembangan Masyarakat, Pengembangan SDM, Sosiologi.
A33: RINGKASAN KONTRIBUSI SKOR
A34: Aspek | B34: R | C34: I | D34: A | E34: S | F34: E | G34: C
A35: Aktivitas | B35: =IFERROR(INDEX(Hasil!$W$5:$W$204,MATCH($B$3,Hasil!$B$5:$B$204,0)),"") -> 7 | C35: =IFERROR(INDEX(Hasil!$X$5:$X$204,MATCH($B$3,Hasil!$B$5:$B$204,0)),"") -> 0 | D35: =IFERROR(INDEX(Hasil!$Y$5:$Y$204,MATCH($B$3,Hasil!$B$5:$B$204,0)),"") -> 0 | E35: =IFERROR(INDEX(Hasil!$Z$5:$Z$204,MATCH($B$3,Hasil!$B$5:$B$204,0)),"") -> 0 | F35: =IFERROR(INDEX(Hasil!$AA$5:$AA$204,MATCH($B$3,Hasil!$B$5:$B$204,0)),"") -> 0 | G35: =IFERROR(INDEX(Hasil!$AB$5:$AB$204,MATCH($B$3,Hasil!$B$5:$B$204,0)),"") -> 0
A36: Kemampuan / Keterampilan | B36: =IFERROR(INDEX(Hasil!$AC$5:$AC$204,MATCH($B$3,Hasil!$B$5:$B$204,0)),"") -> 7 | C36: =IFERROR(INDEX(Hasil!$AD$5:$AD$204,MATCH($B$3,Hasil!$B$5:$B$204,0)),"") -> 0 | D36: =IFERROR(INDEX(Hasil!$AE$5:$AE$204,MATCH($B$3,Hasil!$B$5:$B$204,0)),"") -> 0 | E36: =IFERROR(INDEX(Hasil!$AF$5:$AF$204,MATCH($B$3,Hasil!$B$5:$B$204,0)),"") -> 0 | F36: =IFERROR(INDEX(Hasil!$AG$5:$AG$204,MATCH($B$3,Hasil!$B$5:$B$204,0)),"") -> 0 | G36: =IFERROR(INDEX(Hasil!$AH$5:$AH$204,MATCH($B$3,Hasil!$B$5:$B$204,0)),"") -> 0
A37: Pekerjaan | B37: =IFERROR(INDEX(Hasil!$AI$5:$AI$204,MATCH($B$3,Hasil!$B$5:$B$204,0)),"") -> 7 | C37: =IFERROR(INDEX(Hasil!$AJ$5:$AJ$204,MATCH($B$3,Hasil!$B$5:$B$204,0)),"") -> 0 | D37: =IFERROR(INDEX(Hasil!$AK$5:$AK$204,MATCH($B$3,Hasil!$B$5:$B$204,0)),"") -> 0 | E37: =IFERROR(INDEX(Hasil!$AL$5:$AL$204,MATCH($B$3,Hasil!$B$5:$B$204,0)),"") -> 0 | F37: =IFERROR(INDEX(Hasil!$AM$5:$AM$204,MATCH($B$3,Hasil!$B$5:$B$204,0)),"") -> 0 | G37: =IFERROR(INDEX(Hasil!$AN$5:$AN$204,MATCH($B$3,Hasil!$B$5:$B$204,0)),"") -> 0
A38: Self Estimate | B38: =IFERROR(INDEX(Hasil!$AO$5:$AO$204,MATCH($B$3,Hasil!$B$5:$B$204,0)),"") -> 6 | C38: =IFERROR(INDEX(Hasil!$AP$5:$AP$204,MATCH($B$3,Hasil!$B$5:$B$204,0)),"") -> 4 | D38: =IFERROR(INDEX(Hasil!$AQ$5:$AQ$204,MATCH($B$3,Hasil!$B$5:$B$204,0)),"") -> 8 | E38: =IFERROR(INDEX(Hasil!$AR$5:$AR$204,MATCH($B$3,Hasil!$B$5:$B$204,0)),"") -> 10 | F38: =IFERROR(INDEX(Hasil!$AS$5:$AS$204,MATCH($B$3,Hasil!$B$5:$B$204,0)),"") -> 6 | G38: =IFERROR(INDEX(Hasil!$AT$5:$AT$204,MATCH($B$3,Hasil!$B$5:$B$204,0)),"") -> 12
A39: TOTAL | B39: =IFERROR(INDEX(Hasil!$E$5:$E$204,MATCH($B$3,Hasil!$B$5:$B$204,0)),"") -> 27 | C39: =IFERROR(INDEX(Hasil!$F$5:$F$204,MATCH($B$3,Hasil!$B$5:$B$204,0)),"") -> 4 | D39: =IFERROR(INDEX(Hasil!$G$5:$G$204,MATCH($B$3,Hasil!$B$5:$B$204,0)),"") -> 8 | E39: =IFERROR(INDEX(Hasil!$H$5:$H$204,MATCH($B$3,Hasil!$B$5:$B$204,0)),"") -> 10 | F39: =IFERROR(INDEX(Hasil!$I$5:$I$204,MATCH($B$3,Hasil!$B$5:$B$204,0)),"") -> 6 | G39: =IFERROR(INDEX(Hasil!$J$5:$J$204,MATCH($B$3,Hasil!$B$5:$B$204,0)),"") -> 12
A41: Catatan: hasil RIASEC menggambarkan pola minat karier relatif pada enam tipe Holland. Gunakan bersama informasi akademik, pengalaman, nilai pribadi, dan proses bimbingan; hasil ini bukan diagnosis psikologis.

Sheet Laporan Kelompok
A1: LAPORAN KELOMPOK — HOLLAND RIASEC
A3: Sekolah | B3: SMA Negeri Bengkulu | C3: Kelas | D3: XI . IPA. 1 | E3: Tahun | F3: 2009/2010 | H3: Data Siap | I3: =COUNTIF('entri hasil dari isian siswa'!$HY$5:$HY$204,"OK") -> 7 | J3: Perlu Dilengkapi | K3: =COUNTIF('entri hasil dari isian siswa'!$B$5:$B$204,"<>")-COUNTIF('entri hasil dari isian siswa'!$HY$5:$HY$204,"OK") -> 30
H4: Tinggi | I4: =COUNTIF($N$15:$N$204,"Tinggi") -> 7 | J4: Sedang | K4: =COUNTIF($N$15:$N$204,"Sedang") -> 0 | L4: Rendah | M4: =COUNTIF($N$15:$N$204,"Rendah") -> 0
A5: Tipe | B5: Jumlah Dominan Utama | C5: Rata-rata Skor
A6: R | B6: =COUNTIFS(Hasil!$Q$5:$Q$204,A6,Hasil!$V$5:$V$204,"OK") -> 7 | C6: =IFERROR(SUMIFS(Hasil!$E$5:$E$204,Hasil!$V$5:$V$204,"OK")/COUNTIF(Hasil!$V$5:$V$204,"OK"),0) -> 27
A7: I | B7: =COUNTIFS(Hasil!$Q$5:$Q$204,A7,Hasil!$V$5:$V$204,"OK") -> 0 | C7: =IFERROR(SUMIFS(Hasil!$F$5:$F$204,Hasil!$V$5:$V$204,"OK")/COUNTIF(Hasil!$V$5:$V$204,"OK"),0) -> 4
A8: A | B8: =COUNTIFS(Hasil!$Q$5:$Q$204,A8,Hasil!$V$5:$V$204,"OK") -> 0 | C8: =IFERROR(SUMIFS(Hasil!$G$5:$G$204,Hasil!$V$5:$V$204,"OK")/COUNTIF(Hasil!$V$5:$V$204,"OK"),0) -> 8
A9: S | B9: =COUNTIFS(Hasil!$Q$5:$Q$204,A9,Hasil!$V$5:$V$204,"OK") -> 0 | C9: =IFERROR(SUMIFS(Hasil!$H$5:$H$204,Hasil!$V$5:$V$204,"OK")/COUNTIF(Hasil!$V$5:$V$204,"OK"),0) -> 10
A10: E | B10: =COUNTIFS(Hasil!$Q$5:$Q$204,A10,Hasil!$V$5:$V$204,"OK") -> 0 | C10: =IFERROR(SUMIFS(Hasil!$I$5:$I$204,Hasil!$V$5:$V$204,"OK")/COUNTIF(Hasil!$V$5:$V$204,"OK"),0) -> 6
A11: C | B11: =COUNTIFS(Hasil!$Q$5:$Q$204,A11,Hasil!$V$5:$V$204,"OK") -> 0 | C11: =IFERROR(SUMIFS(Hasil!$J$5:$J$204,Hasil!$V$5:$V$204,"OK")/COUNTIF(Hasil!$V$5:$V$204,"OK"),0) -> 12
A14: No | B14: NIS / ID | C14: Nama Siswa | D14: L/P | E14: R | F14: I | G14: A | H14: S | I14: E | J14: C | K14: Kode RIASEC | L14: Status Data | M14: Pasangan Dominan | N14: Konsistensi
A15: =IF(Hasil!$B5="","",Hasil!A5) -> 1 | B15: =IF(Hasil!$B5="","",Hasil!B5) -> 22001 | C15: =IF(Hasil!$B5="","",Hasil!C5) -> Selly Aljannah | D15: =IF(Hasil!$B5="","",Hasil!D5) -> L | E15: =IF(Hasil!$B5="","",Hasil!E5) -> 27 | F15: =IF(Hasil!$B5="","",Hasil!F5) -> 4 | G15: =IF(Hasil!$B5="","",Hasil!G5) -> 8 | H15: =IF(Hasil!$B5="","",Hasil!H5) -> 10 | ... J15: =IF(Hasil!$B5="","",Hasil!J5) -> 12 | K15: =IF(Hasil!$B5="","",Hasil!T5) -> RCS | L15: =IF(Hasil!$B5="","",Hasil!$V5) -> OK | M15: =IF(Hasil!$B5="","",Hasil!$AU5) -> RC | N15: =IF(Hasil!$B5="","",Hasil!$AV5) -> Tinggi
A16: =IF(Hasil!$B6="","",Hasil!A6) -> 2 | B16: =IF(Hasil!$B6="","",Hasil!B6) -> 22002 | C16: =IF(Hasil!$B6="","",Hasil!C6) -> Siti Solekha | D16: =IF(Hasil!$B6="","",Hasil!D6) -> L | E16: =IF(Hasil!$B6="","",Hasil!E6) -> 27 | F16: =IF(Hasil!$B6="","",Hasil!F6) -> 4 | G16: =IF(Hasil!$B6="","",Hasil!G6) -> 8 | H16: =IF(Hasil!$B6="","",Hasil!H6) -> 10 | ... J16: =IF(Hasil!$B6="","",Hasil!J6) -> 12 | K16: =IF(Hasil!$B6="","",Hasil!T6) -> RCS | L16: =IF(Hasil!$B6="","",Hasil!$V6) -> OK | M16: =IF(Hasil!$B6="","",Hasil!$AU6) -> RC | N16: =IF(Hasil!$B6="","",Hasil!$AV6) -> Tinggi
A17: =IF(Hasil!$B7="","",Hasil!A7) -> 3 | B17: =IF(Hasil!$B7="","",Hasil!B7) -> 22003 | C17: =IF(Hasil!$B7="","",Hasil!C7) -> Sri Panca Lestari | D17: =IF(Hasil!$B7="","",Hasil!D7) -> L | E17: =IF(Hasil!$B7="","",Hasil!E7) -> 27 | F17: =IF(Hasil!$B7="","",Hasil!F7) -> 4 | G17: =IF(Hasil!$B7="","",Hasil!G7) -> 8 | H17: =IF(Hasil!$B7="","",Hasil!H7) -> 10 | ... J17: =IF(Hasil!$B7="","",Hasil!J7) -> 12 | K17: =IF(Hasil!$B7="","",Hasil!T7) -> RCS | L17: =IF(Hasil!$B7="","",Hasil!$V7) -> OK | M17: =IF(Hasil!$B7="","",Hasil!$AU7) -> RC | N17: =IF(Hasil!$B7="","",Hasil!$AV7) -> Tinggi
A18: =IF(Hasil!$B8="","",Hasil!A8) -> 4 | B18: =IF(Hasil!$B8="","",Hasil!B8) -> 22004 | C18: =IF(Hasil!$B8="","",Hasil!C8) -> Widi Hartanto | D18: =IF(Hasil!$B8="","",Hasil!D8) -> L | E18: =IF(Hasil!$B8="","",Hasil!E8) -> 27 | F18: =IF(Hasil!$B8="","",Hasil!F8) -> 4 | G18: =IF(Hasil!$B8="","",Hasil!G8) -> 8 | H18: =IF(Hasil!$B8="","",Hasil!H8) -> 10 | ... J18: =IF(Hasil!$B8="","",Hasil!J8) -> 12 | K18: =IF(Hasil!$B8="","",Hasil!T8) -> RCS | L18: =IF(Hasil!$B8="","",Hasil!$V8) -> OK | M18: =IF(Hasil!$B8="","",Hasil!$AU8) -> RC | N18: =IF(Hasil!$B8="","",Hasil!$AV8) -> Tinggi
A19: =IF(Hasil!$B9="","",Hasil!A9) -> 5 | B19: =IF(Hasil!$B9="","",Hasil!B9) -> 22005 | C19: =IF(Hasil!$B9="","",Hasil!C9) -> Puji Lestari | D19: =IF(Hasil!$B9="","",Hasil!D9) -> L | E19: =IF(Hasil!$B9="","",Hasil!E9) -> 27 | F19: =IF(Hasil!$B9="","",Hasil!F9) -> 4 | G19: =IF(Hasil!$B9="","",Hasil!G9) -> 8 | H19: =IF(Hasil!$B9="","",Hasil!H9) -> 10 | ... J19: =IF(Hasil!$B9="","",Hasil!J9) -> 12 | K19: =IF(Hasil!$B9="","",Hasil!T9) -> RCS | L19: =IF(Hasil!$B9="","",Hasil!$V9) -> OK | M19: =IF(Hasil!$B9="","",Hasil!$AU9) -> RC | N19: =IF(Hasil!$B9="","",Hasil!$AV9) -> Tinggi
A20: =IF(Hasil!$B10="","",Hasil!A10) -> 6 | B20: =IF(Hasil!$B10="","",Hasil!B10) -> 22006 | C20: =IF(Hasil!$B10="","",Hasil!C10) -> Silvia Noviana N | D20: =IF(Hasil!$B10="","",Hasil!D10) -> L | E20: =IF(Hasil!$B10="","",Hasil!E10) -> 27 | F20: =IF(Hasil!$B10="","",Hasil!F10) -> 4 | G20: =IF(Hasil!$B10="","",Hasil!G10) -> 8 | H20: =IF(Hasil!$B10="","",Hasil!H10) -> 10 | ... J20: =IF(Hasil!$B10="","",Hasil!J10) -> 12 | K20: =IF(Hasil!$B10="","",Hasil!T10) -> RCS | L20: =IF(Hasil!$B10="","",Hasil!$V10) -> OK | M20: =IF(Hasil!$B10="","",Hasil!$AU10) -> RC | N20: =IF(Hasil!$B10="","",Hasil!$AV10) -> Tinggi
A21: =IF(Hasil!$B11="","",Hasil!A11) -> 7 | B21: =IF(Hasil!$B11="","",Hasil!B11) -> 22007 | C21: =IF(Hasil!$B11="","",Hasil!C11) -> Sinta Intani Fitriana | D21: =IF(Hasil!$B11="","",Hasil!D11) -> L | E21: =IF(Hasil!$B11="","",Hasil!E11) -> 27 | F21: =IF(Hasil!$B11="","",Hasil!F11) -> 4 | G21: =IF(Hasil!$B11="","",Hasil!G11) -> 8 | H21: =IF(Hasil!$B11="","",Hasil!H11) -> 10 | ... J21: =IF(Hasil!$B11="","",Hasil!J11) -> 12 | K21: =IF(Hasil!$B11="","",Hasil!T11) -> RCS | L21: =IF(Hasil!$B11="","",Hasil!$V11) -> OK | M21: =IF(Hasil!$B11="","",Hasil!$AU11) -> RC | N21: =IF(Hasil!$B11="","",Hasil!$AV11) -> Tinggi
A22: =IF(Hasil!$B12="","",Hasil!A12) -> 8 | B22: =IF(Hasil!$B12="","",Hasil!B12) -> 22008 | C22: =IF(Hasil!$B12="","",Hasil!C12) -> Siti Nur Fadhilah | D22: =IF(Hasil!$B12="","",Hasil!D12) -> L | E22: =IF(Hasil!$B12="","",Hasil!E12) -> 4 | F22: =IF(Hasil!$B12="","",Hasil!F12) -> 0 | G22: =IF(Hasil!$B12="","",Hasil!G12) -> 0 | H22: =IF(Hasil!$B12="","",Hasil!H12) -> 0 | ... J22: =IF(Hasil!$B12="","",Hasil!J12) -> 0 | K22: =IF(Hasil!$B12="","",Hasil!T12) | L22: =IF(Hasil!$B12="","",Hasil!$V12) -> Lengkapi 12 Self Estimate | M22: =IF(Hasil!$B12="","",Hasil!$AU12) | N22: =IF(Hasil!$B12="","",Hasil!$AV12)
A23: =IF(Hasil!$B13="","",Hasil!A13) -> 9 | B23: =IF(Hasil!$B13="","",Hasil!B13) -> 22009 | C23: =IF(Hasil!$B13="","",Hasil!C13) -> Khotimatuz Zuhriyah | D23: =IF(Hasil!$B13="","",Hasil!D13) -> L | E23: =IF(Hasil!$B13="","",Hasil!E13) -> 4 | F23: =IF(Hasil!$B13="","",Hasil!F13) -> 0 | G23: =IF(Hasil!$B13="","",Hasil!G13) -> 0 | H23: =IF(Hasil!$B13="","",Hasil!H13) -> 0 | ... J23: =IF(Hasil!$B13="","",Hasil!J13) -> 0 | K23: =IF(Hasil!$B13="","",Hasil!T13) | L23: =IF(Hasil!$B13="","",Hasil!$V13) -> Lengkapi 12 Self Estimate | M23: =IF(Hasil!$B13="","",Hasil!$AU13) | N23: =IF(Hasil!$B13="","",Hasil!$AV13)
A24: =IF(Hasil!$B14="","",Hasil!A14) -> 10 | B24: =IF(Hasil!$B14="","",Hasil!B14) -> 22010 | C24: =IF(Hasil!$B14="","",Hasil!C14) -> Kukuh Priyatin | D24: =IF(Hasil!$B14="","",Hasil!D14) -> L | E24: =IF(Hasil!$B14="","",Hasil!E14) -> 4 | F24: =IF(Hasil!$B14="","",Hasil!F14) -> 0 | G24: =IF(Hasil!$B14="","",Hasil!G14) -> 0 | H24: =IF(Hasil!$B14="","",Hasil!H14) -> 0 | ... J24: =IF(Hasil!$B14="","",Hasil!J14) -> 0 | K24: =IF(Hasil!$B14="","",Hasil!T14) | L24: =IF(Hasil!$B14="","",Hasil!$V14) -> Lengkapi 12 Self Estimate | M24: =IF(Hasil!$B14="","",Hasil!$AU14) | N24: =IF(Hasil!$B14="","",Hasil!$AV14)
A25: =IF(Hasil!$B15="","",Hasil!A15) -> 11 | B25: =IF(Hasil!$B15="","",Hasil!B15) -> 22011 | C25: =IF(Hasil!$B15="","",Hasil!C15) -> Mas Karebet Setiawan | D25: =IF(Hasil!$B15="","",Hasil!D15) -> L | E25: =IF(Hasil!$B15="","",Hasil!E15) -> 4 | F25: =IF(Hasil!$B15="","",Hasil!F15) -> 0 | G25: =IF(Hasil!$B15="","",Hasil!G15) -> 0 | H25: =IF(Hasil!$B15="","",Hasil!H15) -> 0 | ... J25: =IF(Hasil!$B15="","",Hasil!J15) -> 0 | K25: =IF(Hasil!$B15="","",Hasil!T15) | L25: =IF(Hasil!$B15="","",Hasil!$V15) -> Lengkapi 12 Self Estimate | M25: =IF(Hasil!$B15="","",Hasil!$AU15) | N25: =IF(Hasil!$B15="","",Hasil!$AV15)
A26: =IF(Hasil!$B16="","",Hasil!A16) -> 12 | B26: =IF(Hasil!$B16="","",Hasil!B16) -> 22012 | C26: =IF(Hasil!$B16="","",Hasil!C16) -> Mauidhotul Hasanah Ismail | D26: =IF(Hasil!$B16="","",Hasil!D16) -> L | E26: =IF(Hasil!$B16="","",Hasil!E16) -> 4 | F26: =IF(Hasil!$B16="","",Hasil!F16) -> 0 | G26: =IF(Hasil!$B16="","",Hasil!G16) -> 0 | H26: =IF(Hasil!$B16="","",Hasil!H16) -> 0 | ... J26: =IF(Hasil!$B16="","",Hasil!J16) -> 0 | K26: =IF(Hasil!$B16="","",Hasil!T16) | L26: =IF(Hasil!$B16="","",Hasil!$V16) -> Lengkapi 12 Self Estimate | M26: =IF(Hasil!$B16="","",Hasil!$AU16) | N26: =IF(Hasil!$B16="","",Hasil!$AV16)
... A204: =IF(Hasil!$B194="","",Hasil!A194) | B204: =IF(Hasil!$B194="","",Hasil!B194) | C204: =IF(Hasil!$B194="","",Hasil!C194) | D204: =IF(Hasil!$B194="","",Hasil!D194) | E204: =IF(Hasil!$B194="","",Hasil!E194) | F204: =IF(Hasil!$B194="","",Hasil!F194) | G204: =IF(Hasil!$B194="","",Hasil!G194) | H204: =IF(Hasil!$B194="","",Hasil!H194) | ... J204: =IF(Hasil!$B194="","",Hasil!J194) | K204: =IF(Hasil!$B194="","",Hasil!T194) | L204: =IF(Hasil!$B194="","",Hasil!$V194) | M204: =IF(Hasil!$B194="","",Hasil!$AU194) | N204: =IF(Hasil!$B194="","",Hasil!$AV194)
A205: =IF(Hasil!$B195="","",Hasil!A195) | B205: =IF(Hasil!$B195="","",Hasil!B195) | C205: =IF(Hasil!$B195="","",Hasil!C195) | D205: =IF(Hasil!$B195="","",Hasil!D195) | E205: =IF(Hasil!$B195="","",Hasil!E195) | F205: =IF(Hasil!$B195="","",Hasil!F195) | G205: =IF(Hasil!$B195="","",Hasil!G195) | H205: =IF(Hasil!$B195="","",Hasil!H195) | ... J205: =IF(Hasil!$B195="","",Hasil!J195) | K205: =IF(Hasil!$B195="","",Hasil!T195) | L205: =IF(Hasil!$B195="","",Hasil!$V195)
A206: =IF(Hasil!$B196="","",Hasil!A196) | B206: =IF(Hasil!$B196="","",Hasil!B196) | C206: =IF(Hasil!$B196="","",Hasil!C196) | D206: =IF(Hasil!$B196="","",Hasil!D196) | E206: =IF(Hasil!$B196="","",Hasil!E196) | F206: =IF(Hasil!$B196="","",Hasil!F196) | G206: =IF(Hasil!$B196="","",Hasil!G196) | H206: =IF(Hasil!$B196="","",Hasil!H196) | ... J206: =IF(Hasil!$B196="","",Hasil!J196) | K206: =IF(Hasil!$B196="","",Hasil!T196) | L206: =IF(Hasil!$B196="","",Hasil!$V196)
A207: =IF(Hasil!$B197="","",Hasil!A197) | B207: =IF(Hasil!$B197="","",Hasil!B197) | C207: =IF(Hasil!$B197="","",Hasil!C197) | D207: =IF(Hasil!$B197="","",Hasil!D197) | E207: =IF(Hasil!$B197="","",Hasil!E197) | F207: =IF(Hasil!$B197="","",Hasil!F197) | G207: =IF(Hasil!$B197="","",Hasil!G197) | H207: =IF(Hasil!$B197="","",Hasil!H197) | ... J207: =IF(Hasil!$B197="","",Hasil!J197) | K207: =IF(Hasil!$B197="","",Hasil!T197) | L207: =IF(Hasil!$B197="","",Hasil!$V197)
A208: =IF(Hasil!$B198="","",Hasil!A198) | B208: =IF(Hasil!$B198="","",Hasil!B198) | C208: =IF(Hasil!$B198="","",Hasil!C198) | D208: =IF(Hasil!$B198="","",Hasil!D198) | E208: =IF(Hasil!$B198="","",Hasil!E198) | F208: =IF(Hasil!$B198="","",Hasil!F198) | G208: =IF(Hasil!$B198="","",Hasil!G198) | H208: =IF(Hasil!$B198="","",Hasil!H198) | ... J208: =IF(Hasil!$B198="","",Hasil!J198) | K208: =IF(Hasil!$B198="","",Hasil!T198) | L208: =IF(Hasil!$B198="","",Hasil!$V198)
A209: =IF(Hasil!$B199="","",Hasil!A199) | B209: =IF(Hasil!$B199="","",Hasil!B199) | C209: =IF(Hasil!$B199="","",Hasil!C199) | D209: =IF(Hasil!$B199="","",Hasil!D199) | E209: =IF(Hasil!$B199="","",Hasil!E199) | F209: =IF(Hasil!$B199="","",Hasil!F199) | G209: =IF(Hasil!$B199="","",Hasil!G199) | H209: =IF(Hasil!$B199="","",Hasil!H199) | ... J209: =IF(Hasil!$B199="","",Hasil!J199) | K209: =IF(Hasil!$B199="","",Hasil!T199) | L209: =IF(Hasil!$B199="","",Hasil!$V199)
A210: =IF(Hasil!$B200="","",Hasil!A200) | B210: =IF(Hasil!$B200="","",Hasil!B200) | C210: =IF(Hasil!$B200="","",Hasil!C200) | D210: =IF(Hasil!$B200="","",Hasil!D200) | E210: =IF(Hasil!$B200="","",Hasil!E200) | F210: =IF(Hasil!$B200="","",Hasil!F200) | G210: =IF(Hasil!$B200="","",Hasil!G200) | H210: =IF(Hasil!$B200="","",Hasil!H200) | ... J210: =IF(Hasil!$B200="","",Hasil!J200) | K210: =IF(Hasil!$B200="","",Hasil!T200) | L210: =IF(Hasil!$B200="","",Hasil!$V200)
A211: =IF(Hasil!$B201="","",Hasil!A201) | B211: =IF(Hasil!$B201="","",Hasil!B201) | C211: =IF(Hasil!$B201="","",Hasil!C201) | D211: =IF(Hasil!$B201="","",Hasil!D201) | E211: =IF(Hasil!$B201="","",Hasil!E201) | F211: =IF(Hasil!$B201="","",Hasil!F201) | G211: =IF(Hasil!$B201="","",Hasil!G201) | H211: =IF(Hasil!$B201="","",Hasil!H201) | ... J211: =IF(Hasil!$B201="","",Hasil!J201) | K211: =IF(Hasil!$B201="","",Hasil!T201) | L211: =IF(Hasil!$B201="","",Hasil!$V201)
A212: =IF(Hasil!$B202="","",Hasil!A202) | B212: =IF(Hasil!$B202="","",Hasil!B202) | C212: =IF(Hasil!$B202="","",Hasil!C202) | D212: =IF(Hasil!$B202="","",Hasil!D202) | E212: =IF(Hasil!$B202="","",Hasil!E202) | F212: =IF(Hasil!$B202="","",Hasil!F202) | G212: =IF(Hasil!$B202="","",Hasil!G202) | H212: =IF(Hasil!$B202="","",Hasil!H202) | ... J212: =IF(Hasil!$B202="","",Hasil!J202) | K212: =IF(Hasil!$B202="","",Hasil!T202) | L212: =IF(Hasil!$B202="","",Hasil!$V202)
A213: =IF(Hasil!$B203="","",Hasil!A203) | B213: =IF(Hasil!$B203="","",Hasil!B203) | C213: =IF(Hasil!$B203="","",Hasil!C203) | D213: =IF(Hasil!$B203="","",Hasil!D203) | E213: =IF(Hasil!$B203="","",Hasil!E203) | F213: =IF(Hasil!$B203="","",Hasil!F203) | G213: =IF(Hasil!$B203="","",Hasil!G203) | H213: =IF(Hasil!$B203="","",Hasil!H203) | ... J213: =IF(Hasil!$B203="","",Hasil!J203) | K213: =IF(Hasil!$B203="","",Hasil!T203) | L213: =IF(Hasil!$B203="","",Hasil!$V203)
A214: =IF(Hasil!$B204="","",Hasil!A204) | B214: =IF(Hasil!$B204="","",Hasil!B204) | C214: =IF(Hasil!$B204="","",Hasil!C204) | D214: =IF(Hasil!$B204="","",Hasil!D204) | E214: =IF(Hasil!$B204="","",Hasil!E204) | F214: =IF(Hasil!$B204="","",Hasil!F204) | G214: =IF(Hasil!$B204="","",Hasil!G204) | H214: =IF(Hasil!$B204="","",Hasil!H204) | ... J214: =IF(Hasil!$B204="","",Hasil!J204) | K214: =IF(Hasil!$B204="","",Hasil!T204) | L214: =IF(Hasil!$B204="","",Hasil!$V204)

Sheet Hasil
A1: HASIL PERHITUNGAN RIASEC — KODE 3 HURUF UNIK
A2: Jika skor seri, tie-break tetap R → I → A → S → E → C. Rank unik 1–6 memastikan tiga huruf hasil selalu berbeda.
A4: No | B4: NIS / ID | C4: Nama Siswa | D4: L/P | E4: R | F4: I | G4: A | H4: S | I4: E | J4: C | K4: Rank R | L4: Rank I | M4: Rank A | N4: Rank S | O4: Rank E | P4: Rank C | Q4: Top 1 | R4: Top 2 | S4: Top 3 | T4: Kode RIASEC | U4: Rekomendasi Karier | V4: Status Data | W4: Akt R | X4: Akt I | Y4: Akt A | Z4: Akt S | AA4: Akt E | AB4: Akt C | AC4: Kem R | AD4: Kem I | AE4: Kem A | AF4: Kem S | AG4: Kem E | AH4: Kem C | AI4: Pek R | AJ4: Pek I | AK4: Pek A | AL4: Pek S | AM4: Pek E | AN4: Pek C | AO4: Self R | AP4: Self I | AQ4: Self A | AR4: Self S | AS4: Self E | AT4: Self C | AU4: Pasangan Dominan | AV4: Tingkat Konsistensi
A5: =ROW()-4 -> 1 | B5: =IF('entri hasil dari isian siswa'!B5="","",'entri hasil dari isian siswa'!B5) -> 22001 | C5: =IF('entri hasil dari isian siswa'!C5="","",'entri hasil dari isian siswa'!C5) -> Selly Aljannah | D5: =IF('entri hasil dari isian siswa'!D5="","",'entri hasil dari isian siswa'!D5) -> L | E5: =IF($B5="","",W5+AC5+AI5+AO5) -> 27 | F5: =IF($B5="","",X5+AD5+AJ5+AP5) -> 4 | G5: =IF($B5="","",Y5+AE5+AK5+AQ5) -> 8 | H5: =IF($B5="","",Z5+AF5+AL5+AR5) -> 10 | I5: =IF($B5="","",AA5+AG5+AM5+AS5) -> 6 | J5: =IF($B5="","",AB5+AH5+AN5+AT5) -> 12 | K5: =IF($V5<>"OK","",RANK(E5,$E5:$J5,0)+COUNTIF($E5:E5,E5)-1) -> 1 | L5: =IF($V5<>"OK","",RANK(F5,$E5:$J5,0)+COUNTIF($E5:F5,F5)-1) -> 6 | M5: =IF($V5<>"OK","",RANK(G5,$E5:$J5,0)+COUNTIF($E5:G5,G5)-1) -> 4 | N5: =IF($V5<>"OK","",RANK(H5,$E5:$J5,0)+COUNTIF($E5:H5,H5)-1) -> 3 | O5: =IF($V5<>"OK","",RANK(I5,$E5:$J5,0)+COUNTIF($E5:I5,I5)-1) -> 5 | P5: =IF($V5<>"OK","",RANK(J5,$E5:$J5,0)+COUNTIF($E5:J5,J5)-1) -> 2 | Q5: =IF($V5<>"OK","",INDEX($E$4:$J$4,1,MATCH(1,$K5:$P5,0))) -> R | R5: =IF($V5<>"OK","",INDEX($E$4:$J$4,1,MATCH(2,$K5:$P5,0))) -> C | S5: =IF($V5<>"OK","",INDEX($E$4:$J$4,1,MATCH(3,$K5:$P5,0))) -> S | T5: =IF($V5<>"OK","",Q5&R5&S5) -> RCS | U5: =IF($T5="","",IFERROR(VLOOKUP($T5,'Kunci dari RIASEC'!$A$4:$B$123,2,FALSE),"Rekomendasi belum tersedia")) -> Teknisi quality control; Programmer/operator CNC; Teknisi kalibrasi; Maintenance planner; Production planner; Koordinator layanan teknis terjadwal; Petugas kontrol alat kesehatan; Koordinator operasional bengkel layanan; Teknisi smart manufacturing; Maintenance planning specialist; Ship officer / captain; QA/QC technician; Koordinator otomasi gudang | V5: =IF('entri hasil dari isian siswa'!B5="","",'entri hasil dari isian siswa'!HY5) -> OK | W5: =IF($B5="","",SUM('entri hasil dari isian siswa'!E5:O5)) -> 7 | X5: =IF($B5="","",SUM('entri hasil dari isian siswa'!P5:Z5)) -> 0 | Y5: =IF($B5="","",SUM('entri hasil dari isian siswa'!AA5:AK5)) -> 0 | Z5: =IF($B5="","",SUM('entri hasil dari isian siswa'!AL5:AV5)) -> 0 | AA5: =IF($B5="","",SUM('entri hasil dari isian siswa'!AW5:BG5)) -> 0 | AB5: =IF($B5="","",SUM('entri hasil dari isian siswa'!BH5:BR5)) -> 0 | AC5: =IF($B5="","",SUM('entri hasil dari isian siswa'!BS5:CC5)) -> 7 | AD5: =IF($B5="","",SUM('entri hasil dari isian siswa'!CD5:CN5)) -> 0 | AE5: =IF($B5="","",SUM('entri hasil dari isian siswa'!CO5:CY5)) -> 0 | AF5: =IF($B5="","",SUM('entri hasil dari isian siswa'!CZ5:DJ5)) -> 0 | AG5: =IF($B5="","",SUM('entri hasil dari isian siswa'!DK5:DU5)) -> 0 | AH5: =IF($B5="","",SUM('entri hasil dari isian siswa'!DV5:EF5)) -> 0 | AI5: =IF($B5="","",SUM('entri hasil dari isian siswa'!EG5:ET5)) -> 7 | AJ5: =IF($B5="","",SUM('entri hasil dari isian siswa'!EU5:FH5)) -> 0 | AK5: =IF($B5="","",SUM('entri hasil dari isian siswa'!FI5:FV5)) -> 0 | AL5: =IF($B5="","",SUM('entri hasil dari isian siswa'!FW5:GJ5)) -> 0 | AM5: =IF($B5="","",SUM('entri hasil dari isian siswa'!GK5:GX5)) -> 0 | AN5: =IF($B5="","",SUM('entri hasil dari isian siswa'!GY5:HL5)) -> 0 | AO5: =IF($B5="","",'entri hasil dari isian siswa'!HM5+'entri hasil dari isian siswa'!HS5) -> 6 | AP5: =IF($B5="","",'entri hasil dari isian siswa'!HN5+'entri hasil dari isian siswa'!HT5) -> 4 | AQ5: =IF($B5="","",'entri hasil dari isian siswa'!HO5+'entri hasil dari isian siswa'!HU5) -> 8 | AR5: =IF($B5="","",'entri hasil dari isian siswa'!HP5+'entri hasil dari isian siswa'!HV5) -> 10 | AS5: =IF($B5="","",'entri hasil dari isian siswa'!HQ5+'entri hasil dari isian siswa'!HW5) -> 6 | AT5: =IF($B5="","",'entri hasil dari isian siswa'!HR5+'entri hasil dari isian siswa'!HX5) -> 12 | AU5: =IF($T5="","",LEFT($T5,2)) -> RC | AV5: =IF($AU5="","",IFERROR(VLOOKUP($AU5,'Kunci dari RIASEC'!$J$4:$K$33,2,FALSE),"")) -> Tinggi
A6: =ROW()-4 -> 2 | B6: =IF('entri hasil dari isian siswa'!B6="","",'entri hasil dari isian siswa'!B6) -> 22002 | C6: =IF('entri hasil dari isian siswa'!C6="","",'entri hasil dari isian siswa'!C6) -> Siti Solekha | D6: =IF('entri hasil dari isian siswa'!D6="","",'entri hasil dari isian siswa'!D6) -> L | E6: =IF($B6="","",W6+AC6+AI6+AO6) -> 27 | F6: =IF($B6="","",X6+AD6+AJ6+AP6) -> 4 | G6: =IF($B6="","",Y6+AE6+AK6+AQ6) -> 8 | H6: =IF($B6="","",Z6+AF6+AL6+AR6) -> 10 | I6: =IF($B6="","",AA6+AG6+AM6+AS6) -> 6 | J6: =IF($B6="","",AB6+AH6+AN6+AT6) -> 12 | K6: =IF($V6<>"OK","",RANK(E6,$E6:$J6,0)+COUNTIF($E6:E6,E6)-1) -> 1 | L6: =IF($V6<>"OK","",RANK(F6,$E6:$J6,0)+COUNTIF($E6:F6,F6)-1) -> 6 | M6: =IF($V6<>"OK","",RANK(G6,$E6:$J6,0)+COUNTIF($E6:G6,G6)-1) -> 4 | N6: =IF($V6<>"OK","",RANK(H6,$E6:$J6,0)+COUNTIF($E6:H6,H6)-1) -> 3 | O6: =IF($V6<>"OK","",RANK(I6,$E6:$J6,0)+COUNTIF($E6:I6,I6)-1) -> 5 | P6: =IF($V6<>"OK","",RANK(J6,$E6:$J6,0)+COUNTIF($E6:J6,J6)-1) -> 2 | Q6: =IF($V6<>"OK","",INDEX($E$4:$J$4,1,MATCH(1,$K6:$P6,0))) -> R | R6: =IF($V6<>"OK","",INDEX($E$4:$J$4,1,MATCH(2,$K6:$P6,0))) -> C | S6: =IF($V6<>"OK","",INDEX($E$4:$J$4,1,MATCH(3,$K6:$P6,0))) -> S | T6: =IF($V6<>"OK","",Q6&R6&S6) -> RCS | U6: =IF($T6="","",IFERROR(VLOOKUP($T6,'Kunci dari RIASEC'!$A$4:$B$123,2,FALSE),"Rekomendasi belum tersedia")) -> Teknisi quality control; Programmer/operator CNC; Teknisi kalibrasi; Maintenance planner; Production planner; Koordinator layanan teknis terjadwal; Petugas kontrol alat kesehatan; Koordinator operasional bengkel layanan; Teknisi smart manufacturing; Maintenance planning specialist; Ship officer / captain; QA/QC technician; Koordinator otomasi gudang | V6: =IF('entri hasil dari isian siswa'!B6="","",'entri hasil dari isian siswa'!HY6) -> OK | W6: =IF($B6="","",SUM('entri hasil dari isian siswa'!E6:O6)) -> 7 | X6: =IF($B6="","",SUM('entri hasil dari isian siswa'!P6:Z6)) -> 0 | Y6: =IF($B6="","",SUM('entri hasil dari isian siswa'!AA6:AK6)) -> 0 | Z6: =IF($B6="","",SUM('entri hasil dari isian siswa'!AL6:AV6)) -> 0 | AA6: =IF($B6="","",SUM('entri hasil dari isian siswa'!AW6:BG6)) -> 0 | AB6: =IF($B6="","",SUM('entri hasil dari isian siswa'!BH6:BR6)) -> 0 | AC6: =IF($B6="","",SUM('entri hasil dari isian siswa'!BS6:CC6)) -> 7 | AD6: =IF($B6="","",SUM('entri hasil dari isian siswa'!CD6:CN6)) -> 0 | AE6: =IF($B6="","",SUM('entri hasil dari isian siswa'!CO6:CY6)) -> 0 | AF6: =IF($B6="","",SUM('entri hasil dari isian siswa'!CZ6:DJ6)) -> 0 | AG6: =IF($B6="","",SUM('entri hasil dari isian siswa'!DK6:DU6)) -> 0 | AH6: =IF($B6="","",SUM('entri hasil dari isian siswa'!DV6:EF6)) -> 0 | AI6: =IF($B6="","",SUM('entri hasil dari isian siswa'!EG6:ET6)) -> 7 | AJ6: =IF($B6="","",SUM('entri hasil dari isian siswa'!EU6:FH6)) -> 0 | AK6: =IF($B6="","",SUM('entri hasil dari isian siswa'!FI6:FV6)) -> 0 | AL6: =IF($B6="","",SUM('entri hasil dari isian siswa'!FW6:GJ6)) -> 0 | AM6: =IF($B6="","",SUM('entri hasil dari isian siswa'!GK6:GX6)) -> 0 | AN6: =IF($B6="","",SUM('entri hasil dari isian siswa'!GY6:HL6)) -> 0 | AO6: =IF($B6="","",'entri hasil dari isian siswa'!HM6+'entri hasil dari isian siswa'!HS6) -> 6 | AP6: =IF($B6="","",'entri hasil dari isian siswa'!HN6+'entri hasil dari isian siswa'!HT6) -> 4 | AQ6: =IF($B6="","",'entri hasil dari isian siswa'!HO6+'entri hasil dari isian siswa'!HU6) -> 8 | AR6: =IF($B6="","",'entri hasil dari isian siswa'!HP6+'entri hasil dari isian siswa'!HV6) -> 10 | AS6: =IF($B6="","",'entri hasil dari isian siswa'!HQ6+'entri hasil dari isian siswa'!HW6) -> 6 | AT6: =IF($B6="","",'entri hasil dari isian siswa'!HR6+'entri hasil dari isian siswa'!HX6) -> 12 | AU6: =IF($T6="","",LEFT($T6,2)) -> RC | AV6: =IF($AU6="","",IFERROR(VLOOKUP($AU6,'Kunci dari RIASEC'!$J$4:$K$33,2,FALSE),"")) -> Tinggi
A7: =ROW()-4 -> 3 | B7: =IF('entri hasil dari isian siswa'!B7="","",'entri hasil dari isian siswa'!B7) -> 22003 | C7: =IF('entri hasil dari isian siswa'!C7="","",'entri hasil dari isian siswa'!C7) -> Sri Panca Lestari | D7: =IF('entri hasil dari isian siswa'!D7="","",'entri hasil dari isian siswa'!D7) -> L | E7: =IF($B7="","",W7+AC7+AI7+AO7) -> 27 | F7: =IF($B7="","",X7+AD7+AJ7+AP7) -> 4 | G7: =IF($B7="","",Y7+AE7+AK7+AQ7) -> 8 | H7: =IF($B7="","",Z7+AF7+AL7+AR7) -> 10 | I7: =IF($B7="","",AA7+AG7+AM7+AS7) -> 6 | J7: =IF($B7="","",AB7+AH7+AN7+AT7) -> 12 | K7: =IF($V7<>"OK","",RANK(E7,$E7:$J7,0)+COUNTIF($E7:E7,E7)-1) -> 1 | L7: =IF($V7<>"OK","",RANK(F7,$E7:$J7,0)+COUNTIF($E7:F7,F7)-1) -> 6 | M7: =IF($V7<>"OK","",RANK(G7,$E7:$J7,0)+COUNTIF($E7:G7,G7)-1) -> 4 | N7: =IF($V7<>"OK","",RANK(H7,$E7:$J7,0)+COUNTIF($E7:H7,H7)-1) -> 3 | O7: =IF($V7<>"OK","",RANK(I7,$E7:$J7,0)+COUNTIF($E7:I7,I7)-1) -> 5 | P7: =IF($V7<>"OK","",RANK(J7,$E7:$J7,0)+COUNTIF($E7:J7,J7)-1) -> 2 | Q7: =IF($V7<>"OK","",INDEX($E$4:$J$4,1,MATCH(1,$K7:$P7,0))) -> R | R7: =IF($V7<>"OK","",INDEX($E$4:$J$4,1,MATCH(2,$K7:$P7,0))) -> C | S7: =IF($V7<>"OK","",INDEX($E$4:$J$4,1,MATCH(3,$K7:$P7,0))) -> S | T7: =IF($V7<>"OK","",Q7&R7&S7) -> RCS | U7: =IF($T7="","",IFERROR(VLOOKUP($T7,'Kunci dari RIASEC'!$A$4:$B$123,2,FALSE),"Rekomendasi belum tersedia")) -> Teknisi quality control; Programmer/operator CNC; Teknisi kalibrasi; Maintenance planner; Production planner; Koordinator layanan teknis terjadwal; Petugas kontrol alat kesehatan; Koordinator operasional bengkel layanan; Teknisi smart manufacturing; Maintenance planning specialist; Ship officer / captain; QA/QC technician; Koordinator otomasi gudang | V7: =IF('entri hasil dari isian siswa'!B7="","",'entri hasil dari isian siswa'!HY7) -> OK | W7: =IF($B7="","",SUM('entri hasil dari isian siswa'!E7:O7)) -> 7 | X7: =IF($B7="","",SUM('entri hasil dari isian siswa'!P7:Z7)) -> 0 | Y7: =IF($B7="","",SUM('entri hasil dari isian siswa'!AA7:AK7)) -> 0 | Z7: =IF($B7="","",SUM('entri hasil dari isian siswa'!AL7:AV7)) -> 0 | AA7: =IF($B7="","",SUM('entri hasil dari isian siswa'!AW7:BG7)) -> 0 | AB7: =IF($B7="","",SUM('entri hasil dari isian siswa'!BH7:BR7)) -> 0 | AC7: =IF($B7="","",SUM('entri hasil dari isian siswa'!BS7:CC7)) -> 7 | AD7: =IF($B7="","",SUM('entri hasil dari isian siswa'!CD7:CN7)) -> 0 | AE7: =IF($B7="","",SUM('entri hasil dari isian siswa'!CO7:CY7)) -> 0 | AF7: =IF($B7="","",SUM('entri hasil dari isian siswa'!CZ7:DJ7)) -> 0 | AG7: =IF($B7="","",SUM('entri hasil dari isian siswa'!DK7:DU7)) -> 0 | AH7: =IF($B7="","",SUM('entri hasil dari isian siswa'!DV7:EF7)) -> 0 | AI7: =IF($B7="","",SUM('entri hasil dari isian siswa'!EG7:ET7)) -> 7 | AJ7: =IF($B7="","",SUM('entri hasil dari isian siswa'!EU7:FH7)) -> 0 | AK7: =IF($B7="","",SUM('entri hasil dari isian siswa'!FI7:FV7)) -> 0 | AL7: =IF($B7="","",SUM('entri hasil dari isian siswa'!FW7:GJ7)) -> 0 | AM7: =IF($B7="","",SUM('entri hasil dari isian siswa'!GK7:GX7)) -> 0 | AN7: =IF($B7="","",SUM('entri hasil dari isian siswa'!GY7:HL7)) -> 0 | AO7: =IF($B7="","",'entri hasil dari isian siswa'!HM7+'entri hasil dari isian siswa'!HS7) -> 6 | AP7: =IF($B7="","",'entri hasil dari isian siswa'!HN7+'entri hasil dari isian siswa'!HT7) -> 4 | AQ7: =IF($B7="","",'entri hasil dari isian siswa'!HO7+'entri hasil dari isian siswa'!HU7) -> 8 | AR7: =IF($B7="","",'entri hasil dari isian siswa'!HP7+'entri hasil dari isian siswa'!HV7) -> 10 | AS7: =IF($B7="","",'entri hasil dari isian siswa'!HQ7+'entri hasil dari isian siswa'!HW7) -> 6 | AT7: =IF($B7="","",'entri hasil dari isian siswa'!HR7+'entri hasil dari isian siswa'!HX7) -> 12 | AU7: =IF($T7="","",LEFT($T7,2)) -> RC | AV7: =IF($AU7="","",IFERROR(VLOOKUP($AU7,'Kunci dari RIASEC'!$J$4:$K$33,2,FALSE),"")) -> Tinggi
A8: =ROW()-4 -> 4 | B8: =IF('entri hasil dari isian siswa'!B8="","",'entri hasil dari isian siswa'!B8) -> 22004 | C8: =IF('entri hasil dari isian siswa'!C8="","",'entri hasil dari isian siswa'!C8) -> Widi Hartanto | D8: =IF('entri hasil dari isian siswa'!D8="","",'entri hasil dari isian siswa'!D8) -> L | E8: =IF($B8="","",W8+AC8+AI8+AO8) -> 27 | F8: =IF($B8="","",X8+AD8+AJ8+AP8) -> 4 | G8: =IF($B8="","",Y8+AE8+AK8+AQ8) -> 8 | H8: =IF($B8="","",Z8+AF8+AL8+AR8) -> 10 | I8: =IF($B8="","",AA8+AG8+AM8+AS8) -> 6 | J8: =IF($B8="","",AB8+AH8+AN8+AT8) -> 12 | K8: =IF($V8<>"OK","",RANK(E8,$E8:$J8,0)+COUNTIF($E8:E8,E8)-1) -> 1 | L8: =IF($V8<>"OK","",RANK(F8,$E8:$J8,0)+COUNTIF($E8:F8,F8)-1) -> 6 | M8: =IF($V8<>"OK","",RANK(G8,$E8:$J8,0)+COUNTIF($E8:G8,G8)-1) -> 4 | N8: =IF($V8<>"OK","",RANK(H8,$E8:$J8,0)+COUNTIF($E8:H8,H8)-1) -> 3 | O8: =IF($V8<>"OK","",RANK(I8,$E8:$J8,0)+COUNTIF($E8:I8,I8)-1) -> 5 | P8: =IF($V8<>"OK","",RANK(J8,$E8:$J8,0)+COUNTIF($E8:J8,J8)-1) -> 2 | Q8: =IF($V8<>"OK","",INDEX($E$4:$J$4,1,MATCH(1,$K8:$P8,0))) -> R | R8: =IF($V8<>"OK","",INDEX($E$4:$J$4,1,MATCH(2,$K8:$P8,0))) -> C | S8: =IF($V8<>"OK","",INDEX($E$4:$J$4,1,MATCH(3,$K8:$P8,0))) -> S | T8: =IF($V8<>"OK","",Q8&R8&S8) -> RCS | U8: =IF($T8="","",IFERROR(VLOOKUP($T8,'Kunci dari RIASEC'!$A$4:$B$123,2,FALSE),"Rekomendasi belum tersedia")) -> Teknisi quality control; Programmer/operator CNC; Teknisi kalibrasi; Maintenance planner; Production planner; Koordinator layanan teknis terjadwal; Petugas kontrol alat kesehatan; Koordinator operasional bengkel layanan; Teknisi smart manufacturing; Maintenance planning specialist; Ship officer / captain; QA/QC technician; Koordinator otomasi gudang | V8: =IF('entri hasil dari isian siswa'!B8="","",'entri hasil dari isian siswa'!HY8) -> OK | W8: =IF($B8="","",SUM('entri hasil dari isian siswa'!E8:O8)) -> 7 | X8: =IF($B8="","",SUM('entri hasil dari isian siswa'!P8:Z8)) -> 0 | Y8: =IF($B8="","",SUM('entri hasil dari isian siswa'!AA8:AK8)) -> 0 | Z8: =IF($B8="","",SUM('entri hasil dari isian siswa'!AL8:AV8)) -> 0 | AA8: =IF($B8="","",SUM('entri hasil dari isian siswa'!AW8:BG8)) -> 0 | AB8: =IF($B8="","",SUM('entri hasil dari isian siswa'!BH8:BR8)) -> 0 | AC8: =IF($B8="","",SUM('entri hasil dari isian siswa'!BS8:CC8)) -> 7 | AD8: =IF($B8="","",SUM('entri hasil dari isian siswa'!CD8:CN8)) -> 0 | AE8: =IF($B8="","",SUM('entri hasil dari isian siswa'!CO8:CY8)) -> 0 | AF8: =IF($B8="","",SUM('entri hasil dari isian siswa'!CZ8:DJ8)) -> 0 | AG8: =IF($B8="","",SUM('entri hasil dari isian siswa'!DK8:DU8)) -> 0 | AH8: =IF($B8="","",SUM('entri hasil dari isian siswa'!DV8:EF8)) -> 0 | AI8: =IF($B8="","",SUM('entri hasil dari isian siswa'!EG8:ET8)) -> 7 | AJ8: =IF($B8="","",SUM('entri hasil dari isian siswa'!EU8:FH8)) -> 0 | AK8: =IF($B8="","",SUM('entri hasil dari isian siswa'!FI8:FV8)) -> 0 | AL8: =IF($B8="","",SUM('entri hasil dari isian siswa'!FW8:GJ8)) -> 0 | AM8: =IF($B8="","",SUM('entri hasil dari isian siswa'!GK8:GX8)) -> 0 | AN8: =IF($B8="","",SUM('entri hasil dari isian siswa'!GY8:HL8)) -> 0 | AO8: =IF($B8="","",'entri hasil dari isian siswa'!HM8+'entri hasil dari isian siswa'!HS8) -> 6 | AP8: =IF($B8="","",'entri hasil dari isian siswa'!HN8+'entri hasil dari isian siswa'!HT8) -> 4 | AQ8: =IF($B8="","",'entri hasil dari isian siswa'!HO8+'entri hasil dari isian siswa'!HU8) -> 8 | AR8: =IF($B8="","",'entri hasil dari isian siswa'!HP8+'entri hasil dari isian siswa'!HV8) -> 10 | AS8: =IF($B8="","",'entri hasil dari isian siswa'!HQ8+'entri hasil dari isian siswa'!HW8) -> 6 | AT8: =IF($B8="","",'entri hasil dari isian siswa'!HR8+'entri hasil dari isian siswa'!HX8) -> 12 | AU8: =IF($T8="","",LEFT($T8,2)) -> RC | AV8: =IF($AU8="","",IFERROR(VLOOKUP($AU8,'Kunci dari RIASEC'!$J$4:$K$33,2,FALSE),"")) -> Tinggi
A9: =ROW()-4 -> 5 | B9: =IF('entri hasil dari isian siswa'!B9="","",'entri hasil dari isian siswa'!B9) -> 22005 | C9: =IF('entri hasil dari isian siswa'!C9="","",'entri hasil dari isian siswa'!C9) -> Puji Lestari | D9: =IF('entri hasil dari isian siswa'!D9="","",'entri hasil dari isian siswa'!D9) -> L | E9: =IF($B9="","",W9+AC9+AI9+AO9) -> 27 | F9: =IF($B9="","",X9+AD9+AJ9+AP9) -> 4 | G9: =IF($B9="","",Y9+AE9+AK9+AQ9) -> 8 | H9: =IF($B9="","",Z9+AF9+AL9+AR9) -> 10 | I9: =IF($B9="","",AA9+AG9+AM9+AS9) -> 6 | J9: =IF($B9="","",AB9+AH9+AN9+AT9) -> 12 | K9: =IF($V9<>"OK","",RANK(E9,$E9:$J9,0)+COUNTIF($E9:E9,E9)-1) -> 1 | L9: =IF($V9<>"OK","",RANK(F9,$E9:$J9,0)+COUNTIF($E9:F9,F9)-1) -> 6 | M9: =IF($V9<>"OK","",RANK(G9,$E9:$J9,0)+COUNTIF($E9:G9,G9)-1) -> 4 | N9: =IF($V9<>"OK","",RANK(H9,$E9:$J9,0)+COUNTIF($E9:H9,H9)-1) -> 3 | O9: =IF($V9<>"OK","",RANK(I9,$E9:$J9,0)+COUNTIF($E9:I9,I9)-1) -> 5 | P9: =IF($V9<>"OK","",RANK(J9,$E9:$J9,0)+COUNTIF($E9:J9,J9)-1) -> 2 | Q9: =IF($V9<>"OK","",INDEX($E$4:$J$4,1,MATCH(1,$K9:$P9,0))) -> R | R9: =IF($V9<>"OK","",INDEX($E$4:$J$4,1,MATCH(2,$K9:$P9,0))) -> C | S9: =IF($V9<>"OK","",INDEX($E$4:$J$4,1,MATCH(3,$K9:$P9,0))) -> S | T9: =IF($V9<>"OK","",Q9&R9&S9) -> RCS | U9: =IF($T9="","",IFERROR(VLOOKUP($T9,'Kunci dari RIASEC'!$A$4:$B$123,2,FALSE),"Rekomendasi belum tersedia")) -> Teknisi quality control; Programmer/operator CNC; Teknisi kalibrasi; Maintenance planner; Production planner; Koordinator layanan teknis terjadwal; Petugas kontrol alat kesehatan; Koordinator operasional bengkel layanan; Teknisi smart manufacturing; Maintenance planning specialist; Ship officer / captain; QA/QC technician; Koordinator otomasi gudang | V9: =IF('entri hasil dari isian siswa'!B9="","",'entri hasil dari isian siswa'!HY9) -> OK | W9: =IF($B9="","",SUM('entri hasil dari isian siswa'!E9:O9)) -> 7 | X9: =IF($B9="","",SUM('entri hasil dari isian siswa'!P9:Z9)) -> 0 | Y9: =IF($B9="","",SUM('entri hasil dari isian siswa'!AA9:AK9)) -> 0 | Z9: =IF($B9="","",SUM('entri hasil dari isian siswa'!AL9:AV9)) -> 0 | AA9: =IF($B9="","",SUM('entri hasil dari isian siswa'!AW9:BG9)) -> 0 | AB9: =IF($B9="","",SUM('entri hasil dari isian siswa'!BH9:BR9)) -> 0 | AC9: =IF($B9="","",SUM('entri hasil dari isian siswa'!BS9:CC9)) -> 7 | AD9: =IF($B9="","",SUM('entri hasil dari isian siswa'!CD9:CN9)) -> 0 | AE9: =IF($B9="","",SUM('entri hasil dari isian siswa'!CO9:CY9)) -> 0 | AF9: =IF($B9="","",SUM('entri hasil dari isian siswa'!CZ9:DJ9)) -> 0 | AG9: =IF($B9="","",SUM('entri hasil dari isian siswa'!DK9:DU9)) -> 0 | AH9: =IF($B9="","",SUM('entri hasil dari isian siswa'!DV9:EF9)) -> 0 | AI9: =IF($B9="","",SUM('entri hasil dari isian siswa'!EG9:ET9)) -> 7 | AJ9: =IF($B9="","",SUM('entri hasil dari isian siswa'!EU9:FH9)) -> 0 | AK9: =IF($B9="","",SUM('entri hasil dari isian siswa'!FI9:FV9)) -> 0 | AL9: =IF($B9="","",SUM('entri hasil dari isian siswa'!FW9:GJ9)) -> 0 | AM9: =IF($B9="","",SUM('entri hasil dari isian siswa'!GK9:GX9)) -> 0 | AN9: =IF($B9="","",SUM('entri hasil dari isian siswa'!GY9:HL9)) -> 0 | AO9: =IF($B9="","",'entri hasil dari isian siswa'!HM9+'entri hasil dari isian siswa'!HS9) -> 6 | AP9: =IF($B9="","",'entri hasil dari isian siswa'!HN9+'entri hasil dari isian siswa'!HT9) -> 4 | AQ9: =IF($B9="","",'entri hasil dari isian siswa'!HO9+'entri hasil dari isian siswa'!HU9) -> 8 | AR9: =IF($B9="","",'entri hasil dari isian siswa'!HP9+'entri hasil dari isian siswa'!HV9) -> 10 | AS9: =IF($B9="","",'entri hasil dari isian siswa'!HQ9+'entri hasil dari isian siswa'!HW9) -> 6 | AT9: =IF($B9="","",'entri hasil dari isian siswa'!HR9+'entri hasil dari isian siswa'!HX9) -> 12 | AU9: =IF($T9="","",LEFT($T9,2)) -> RC | AV9: =IF($AU9="","",IFERROR(VLOOKUP($AU9,'Kunci dari RIASEC'!$J$4:$K$33,2,FALSE),"")) -> Tinggi
A10: =ROW()-4 -> 6 | B10: =IF('entri hasil dari isian siswa'!B10="","",'entri hasil dari isian siswa'!B10) -> 22006 | C10: =IF('entri hasil dari isian siswa'!C10="","",'entri hasil dari isian siswa'!C10) -> Silvia Noviana N | D10: =IF('entri hasil dari isian siswa'!D10="","",'entri hasil dari isian siswa'!D10) -> L | E10: =IF($B10="","",W10+AC10+AI10+AO10) -> 27 | F10: =IF($B10="","",X10+AD10+AJ10+AP10) -> 4 | G10: =IF($B10="","",Y10+AE10+AK10+AQ10) -> 8 | H10: =IF($B10="","",Z10+AF10+AL10+AR10) -> 10 | I10: =IF($B10="","",AA10+AG10+AM10+AS10) -> 6 | J10: =IF($B10="","",AB10+AH10+AN10+AT10) -> 12 | K10: =IF($V10<>"OK","",RANK(E10,$E10:$J10,0)+COUNTIF($E10:E10,E10)-1) -> 1 | L10: =IF($V10<>"OK","",RANK(F10,$E10:$J10,0)+COUNTIF($E10:F10,F10)-1) -> 6 | M10: =IF($V10<>"OK","",RANK(G10,$E10:$J10,0)+COUNTIF($E10:G10,G10)-1) -> 4 | N10: =IF($V10<>"OK","",RANK(H10,$E10:$J10,0)+COUNTIF($E10:H10,H10)-1) -> 3 | O10: =IF($V10<>"OK","",RANK(I10,$E10:$J10,0)+COUNTIF($E10:I10,I10)-1) -> 5 | P10: =IF($V10<>"OK","",RANK(J10,$E10:$J10,0)+COUNTIF($E10:J10,J10)-1) -> 2 | Q10: =IF($V10<>"OK","",INDEX($E$4:$J$4,1,MATCH(1,$K10:$P10,0))) -> R | R10: =IF($V10<>"OK","",INDEX($E$4:$J$4,1,MATCH(2,$K10:$P10,0))) -> C | S10: =IF($V10<>"OK","",INDEX($E$4:$J$4,1,MATCH(3,$K10:$P10,0))) -> S | T10: =IF($V10<>"OK","",Q10&R10&S10) -> RCS | U10: =IF($T10="","",IFERROR(VLOOKUP($T10,'Kunci dari RIASEC'!$A$4:$B$123,2,FALSE),"Rekomendasi belum tersedia")) -> Teknisi quality control; Programmer/operator CNC; Teknisi kalibrasi; Maintenance planner; Production planner; Koordinator layanan teknis terjadwal; Petugas kontrol alat kesehatan; Koordinator operasional bengkel layanan; Teknisi smart manufacturing; Maintenance planning specialist; Ship officer / captain; QA/QC technician; Koordinator otomasi gudang | V10: =IF('entri hasil dari isian siswa'!B10="","",'entri hasil dari isian siswa'!HY10) -> OK | W10: =IF($B10="","",SUM('entri hasil dari isian siswa'!E10:O10)) -> 7 | X10: =IF($B10="","",SUM('entri hasil dari isian siswa'!P10:Z10)) -> 0 | Y10: =IF($B10="","",SUM('entri hasil dari isian siswa'!AA10:AK10)) -> 0 | Z10: =IF($B10="","",SUM('entri hasil dari isian siswa'!AL10:AV10)) -> 0 | AA10: =IF($B10="","",SUM('entri hasil dari isian siswa'!AW10:BG10)) -> 0 | AB10: =IF($B10="","",SUM('entri hasil dari isian siswa'!BH10:BR10)) -> 0 | AC10: =IF($B10="","",SUM('entri hasil dari isian siswa'!BS10:CC10)) -> 7 | AD10: =IF($B10="","",SUM('entri hasil dari isian siswa'!CD10:CN10)) -> 0 | AE10: =IF($B10="","",SUM('entri hasil dari isian siswa'!CO10:CY10)) -> 0 | AF10: =IF($B10="","",SUM('entri hasil dari isian siswa'!CZ10:DJ10)) -> 0 | AG10: =IF($B10="","",SUM('entri hasil dari isian siswa'!DK10:DU10)) -> 0 | AH10: =IF($B10="","",SUM('entri hasil dari isian siswa'!DV10:EF10)) -> 0 | AI10: =IF($B10="","",SUM('entri hasil dari isian siswa'!EG10:ET10)) -> 7 | AJ10: =IF($B10="","",SUM('entri hasil dari isian siswa'!EU10:FH10)) -> 0 | AK10: =IF($B10="","",SUM('entri hasil dari isian siswa'!FI10:FV10)) -> 0 | AL10: =IF($B10="","",SUM('entri hasil dari isian siswa'!FW10:GJ10)) -> 0 | AM10: =IF($B10="","",SUM('entri hasil dari isian siswa'!GK10:GX10)) -> 0 | AN10: =IF($B10="","",SUM('entri hasil dari isian siswa'!GY10:HL10)) -> 0 | AO10: =IF($B10="","",'entri hasil dari isian siswa'!HM10+'entri hasil dari isian siswa'!HS10) -> 6 | AP10: =IF($B10="","",'entri hasil dari isian siswa'!HN10+'entri hasil dari isian siswa'!HT10) -> 4 | AQ10: =IF($B10="","",'entri hasil dari isian siswa'!HO10+'entri hasil dari isian siswa'!HU10) -> 8 | AR10: =IF($B10="","",'entri hasil dari isian siswa'!HP10+'entri hasil dari isian siswa'!HV10) -> 10 | AS10: =IF($B10="","",'entri hasil dari isian siswa'!HQ10+'entri hasil dari isian siswa'!HW10) -> 6 | AT10: =IF($B10="","",'entri hasil dari isian siswa'!HR10+'entri hasil dari isian siswa'!HX10) -> 12 | AU10: =IF($T10="","",LEFT($T10,2)) -> RC | AV10: =IF($AU10="","",IFERROR(VLOOKUP($AU10,'Kunci dari RIASEC'!$J$4:$K$33,2,FALSE),"")) -> Tinggi
A11: =ROW()-4 -> 7 | B11: =IF('entri hasil dari isian siswa'!B11="","",'entri hasil dari isian siswa'!B11) -> 22007 | C11: =IF('entri hasil dari isian siswa'!C11="","",'entri hasil dari isian siswa'!C11) -> Sinta Intani Fitriana | D11: =IF('entri hasil dari isian siswa'!D11="","",'entri hasil dari isian siswa'!D11) -> L | E11: =IF($B11="","",W11+AC11+AI11+AO11) -> 27 | F11: =IF($B11="","",X11+AD11+AJ11+AP11) -> 4 | G11: =IF($B11="","",Y11+AE11+AK11+AQ11) -> 8 | H11: =IF($B11="","",Z11+AF11+AL11+AR11) -> 10 | I11: =IF($B11="","",AA11+AG11+AM11+AS11) -> 6 | J11: =IF($B11="","",AB11+AH11+AN11+AT11) -> 12 | K11: =IF($V11<>"OK","",RANK(E11,$E11:$J11,0)+COUNTIF($E11:E11,E11)-1) -> 1 | L11: =IF($V11<>"OK","",RANK(F11,$E11:$J11,0)+COUNTIF($E11:F11,F11)-1) -> 6 | M11: =IF($V11<>"OK","",RANK(G11,$E11:$J11,0)+COUNTIF($E11:G11,G11)-1) -> 4 | N11: =IF($V11<>"OK","",RANK(H11,$E11:$J11,0)+COUNTIF($E11:H11,H11)-1) -> 3 | O11: =IF($V11<>"OK","",RANK(I11,$E11:$J11,0)+COUNTIF($E11:I11,I11)-1) -> 5 | P11: =IF($V11<>"OK","",RANK(J11,$E11:$J11,0)+COUNTIF($E11:J11,J11)-1) -> 2 | Q11: =IF($V11<>"OK","",INDEX($E$4:$J$4,1,MATCH(1,$K11:$P11,0))) -> R | R11: =IF($V11<>"OK","",INDEX($E$4:$J$4,1,MATCH(2,$K11:$P11,0))) -> C | S11: =IF($V11<>"OK","",INDEX($E$4:$J$4,1,MATCH(3,$K11:$P11,0))) -> S | T11: =IF($V11<>"OK","",Q11&R11&S11) -> RCS | U11: =IF($T11="","",IFERROR(VLOOKUP($T11,'Kunci dari RIASEC'!$A$4:$B$123,2,FALSE),"Rekomendasi belum tersedia")) -> Teknisi quality control; Programmer/operator CNC; Teknisi kalibrasi; Maintenance planner; Production planner; Koordinator layanan teknis terjadwal; Petugas kontrol alat kesehatan; Koordinator operasional bengkel layanan; Teknisi smart manufacturing; Maintenance planning specialist; Ship officer / captain; QA/QC technician; Koordinator otomasi gudang | V11: =IF('entri hasil dari isian siswa'!B11="","",'entri hasil dari isian siswa'!HY11) -> OK | W11: =IF($B11="","",SUM('entri hasil dari isian siswa'!E11:O11)) -> 7 | X11: =IF($B11="","",SUM('entri hasil dari isian siswa'!P11:Z11)) -> 0 | Y11: =IF($B11="","",SUM('entri hasil dari isian siswa'!AA11:AK11)) -> 0 | Z11: =IF($B11="","",SUM('entri hasil dari isian siswa'!AL11:AV11)) -> 0 | AA11: =IF($B11="","",SUM('entri hasil dari isian siswa'!AW11:BG11)) -> 0 | AB11: =IF($B11="","",SUM('entri hasil dari isian siswa'!BH11:BR11)) -> 0 | AC11: =IF($B11="","",SUM('entri hasil dari isian siswa'!BS11:CC11)) -> 7 | AD11: =IF($B11="","",SUM('entri hasil dari isian siswa'!CD11:CN11)) -> 0 | AE11: =IF($B11="","",SUM('entri hasil dari isian siswa'!CO11:CY11)) -> 0 | AF11: =IF($B11="","",SUM('entri hasil dari isian siswa'!CZ11:DJ11)) -> 0 | AG11: =IF($B11="","",SUM('entri hasil dari isian siswa'!DK11:DU11)) -> 0 | AH11: =IF($B11="","",SUM('entri hasil dari isian siswa'!DV11:EF11)) -> 0 | AI11: =IF($B11="","",SUM('entri hasil dari isian siswa'!EG11:ET11)) -> 7 | AJ11: =IF($B11="","",SUM('entri hasil dari isian siswa'!EU11:FH11)) -> 0 | AK11: =IF($B11="","",SUM('entri hasil dari isian siswa'!FI11:FV11)) -> 0 | AL11: =IF($B11="","",SUM('entri hasil dari isian siswa'!FW11:GJ11)) -> 0 | AM11: =IF($B11="","",SUM('entri hasil dari isian siswa'!GK11:GX11)) -> 0 | AN11: =IF($B11="","",SUM('entri hasil dari isian siswa'!GY11:HL11)) -> 0 | AO11: =IF($B11="","",'entri hasil dari isian siswa'!HM11+'entri hasil dari isian siswa'!HS11) -> 6 | AP11: =IF($B11="","",'entri hasil dari isian siswa'!HN11+'entri hasil dari isian siswa'!HT11) -> 4 | AQ11: =IF($B11="","",'entri hasil dari isian siswa'!HO11+'entri hasil dari isian siswa'!HU11) -> 8 | AR11: =IF($B11="","",'entri hasil dari isian siswa'!HP11+'entri hasil dari isian siswa'!HV11) -> 10 | AS11: =IF($B11="","",'entri hasil dari isian siswa'!HQ11+'entri hasil dari isian siswa'!HW11) -> 6 | AT11: =IF($B11="","",'entri hasil dari isian siswa'!HR11+'entri hasil dari isian siswa'!HX11) -> 12 | AU11: =IF($T11="","",LEFT($T11,2)) -> RC | AV11: =IF($AU11="","",IFERROR(VLOOKUP($AU11,'Kunci dari RIASEC'!$J$4:$K$33,2,FALSE),"")) -> Tinggi
A12: =ROW()-4 -> 8 | B12: =IF('entri hasil dari isian siswa'!B12="","",'entri hasil dari isian siswa'!B12) -> 22008 | C12: =IF('entri hasil dari isian siswa'!C12="","",'entri hasil dari isian siswa'!C12) -> Siti Nur Fadhilah | D12: =IF('entri hasil dari isian siswa'!D12="","",'entri hasil dari isian siswa'!D12) -> L | E12: =IF($B12="","",W12+AC12+AI12+AO12) -> 4 | F12: =IF($B12="","",X12+AD12+AJ12+AP12) -> 0 | G12: =IF($B12="","",Y12+AE12+AK12+AQ12) -> 0 | H12: =IF($B12="","",Z12+AF12+AL12+AR12) -> 0 | I12: =IF($B12="","",AA12+AG12+AM12+AS12) -> 0 | J12: =IF($B12="","",AB12+AH12+AN12+AT12) -> 0 | K12: =IF($V12<>"OK","",RANK(E12,$E12:$J12,0)+COUNTIF($E12:E12,E12)-1) | L12: =IF($V12<>"OK","",RANK(F12,$E12:$J12,0)+COUNTIF($E12:F12,F12)-1) | M12: =IF($V12<>"OK","",RANK(G12,$E12:$J12,0)+COUNTIF($E12:G12,G12)-1) | N12: =IF($V12<>"OK","",RANK(H12,$E12:$J12,0)+COUNTIF($E12:H12,H12)-1) | O12: =IF($V12<>"OK","",RANK(I12,$E12:$J12,0)+COUNTIF($E12:I12,I12)-1) | P12: =IF($V12<>"OK","",RANK(J12,$E12:$J12,0)+COUNTIF($E12:J12,J12)-1) | Q12: =IF($V12<>"OK","",INDEX($E$4:$J$4,1,MATCH(1,$K12:$P12,0))) | R12: =IF($V12<>"OK","",INDEX($E$4:$J$4,1,MATCH(2,$K12:$P12,0))) | S12: =IF($V12<>"OK","",INDEX($E$4:$J$4,1,MATCH(3,$K12:$P12,0))) | T12: =IF($V12<>"OK","",Q12&R12&S12) | U12: =IF($T12="","",IFERROR(VLOOKUP($T12,'Kunci dari RIASEC'!$A$4:$B$123,2,FALSE),"Rekomendasi belum tersedia")) | V12: =IF('entri hasil dari isian siswa'!B12="","",'entri hasil dari isian siswa'!HY12) -> Lengkapi 12 Self Estimate | W12: =IF($B12="","",SUM('entri hasil dari isian siswa'!E12:O12)) -> 4 | X12: =IF($B12="","",SUM('entri hasil dari isian siswa'!P12:Z12)) -> 0 | Y12: =IF($B12="","",SUM('entri hasil dari isian siswa'!AA12:AK12)) -> 0 | Z12: =IF($B12="","",SUM('entri hasil dari isian siswa'!AL12:AV12)) -> 0 | AA12: =IF($B12="","",SUM('entri hasil dari isian siswa'!AW12:BG12)) -> 0 | AB12: =IF($B12="","",SUM('entri hasil dari isian siswa'!BH12:BR12)) -> 0 | AC12: =IF($B12="","",SUM('entri hasil dari isian siswa'!BS12:CC12)) -> 0 | AD12: =IF($B12="","",SUM('entri hasil dari isian siswa'!CD12:CN12)) -> 0 | AE12: =IF($B12="","",SUM('entri hasil dari isian siswa'!CO12:CY12)) -> 0 | AF12: =IF($B12="","",SUM('entri hasil dari isian siswa'!CZ12:DJ12)) -> 0 | AG12: =IF($B12="","",SUM('entri hasil dari isian siswa'!DK12:DU12)) -> 0 | AH12: =IF($B12="","",SUM('entri hasil dari isian siswa'!DV12:EF12)) -> 0 | AI12: =IF($B12="","",SUM('entri hasil dari isian siswa'!EG12:ET12)) -> 0 | AJ12: =IF($B12="","",SUM('entri hasil dari isian siswa'!EU12:FH12)) -> 0 | AK12: =IF($B12="","",SUM('entri hasil dari isian siswa'!FI12:FV12)) -> 0 | AL12: =IF($B12="","",SUM('entri hasil dari isian siswa'!FW12:GJ12)) -> 0 | AM12: =IF($B12="","",SUM('entri hasil dari isian siswa'!GK12:GX12)) -> 0 | AN12: =IF($B12="","",SUM('entri hasil dari isian siswa'!GY12:HL12)) -> 0 | AO12: =IF($B12="","",'entri hasil dari isian siswa'!HM12+'entri hasil dari isian siswa'!HS12) -> 0 | AP12: =IF($B12="","",'entri hasil dari isian siswa'!HN12+'entri hasil dari isian siswa'!HT12) -> 0 | AQ12: =IF($B12="","",'entri hasil dari isian siswa'!HO12+'entri hasil dari isian siswa'!HU12) -> 0 | AR12: =IF($B12="","",'entri hasil dari isian siswa'!HP12+'entri hasil dari isian siswa'!HV12) -> 0 | AS12: =IF($B12="","",'entri hasil dari isian siswa'!HQ12+'entri hasil dari isian siswa'!HW12) -> 0 | AT12: =IF($B12="","",'entri hasil dari isian siswa'!HR12+'entri hasil dari isian siswa'!HX12) -> 0 | AU12: =IF($T12="","",LEFT($T12,2)) | AV12: =IF($AU12="","",IFERROR(VLOOKUP($AU12,'Kunci dari RIASEC'!$J$4:$K$33,2,FALSE),""))
A13: =ROW()-4 -> 9 | B13: =IF('entri hasil dari isian siswa'!B13="","",'entri hasil dari isian siswa'!B13) -> 22009 | C13: =IF('entri hasil dari isian siswa'!C13="","",'entri hasil dari isian siswa'!C13) -> Khotimatuz Zuhriyah | D13: =IF('entri hasil dari isian siswa'!D13="","",'entri hasil dari isian siswa'!D13) -> L | E13: =IF($B13="","",W13+AC13+AI13+AO13) -> 4 | F13: =IF($B13="","",X13+AD13+AJ13+AP13) -> 0 | G13: =IF($B13="","",Y13+AE13+AK13+AQ13) -> 0 | H13: =IF($B13="","",Z13+AF13+AL13+AR13) -> 0 | I13: =IF($B13="","",AA13+AG13+AM13+AS13) -> 0 | J13: =IF($B13="","",AB13+AH13+AN13+AT13) -> 0 | K13: =IF($V13<>"OK","",RANK(E13,$E13:$J13,0)+COUNTIF($E13:E13,E13)-1) | L13: =IF($V13<>"OK","",RANK(F13,$E13:$J13,0)+COUNTIF($E13:F13,F13)-1) | M13: =IF($V13<>"OK","",RANK(G13,$E13:$J13,0)+COUNTIF($E13:G13,G13)-1) | N13: =IF($V13<>"OK","",RANK(H13,$E13:$J13,0)+COUNTIF($E13:H13,H13)-1) | O13: =IF($V13<>"OK","",RANK(I13,$E13:$J13,0)+COUNTIF($E13:I13,I13)-1) | P13: =IF($V13<>"OK","",RANK(J13,$E13:$J13,0)+COUNTIF($E13:J13,J13)-1) | Q13: =IF($V13<>"OK","",INDEX($E$4:$J$4,1,MATCH(1,$K13:$P13,0))) | R13: =IF($V13<>"OK","",INDEX($E$4:$J$4,1,MATCH(2,$K13:$P13,0))) | S13: =IF($V13<>"OK","",INDEX($E$4:$J$4,1,MATCH(3,$K13:$P13,0))) | T13: =IF($V13<>"OK","",Q13&R13&S13) | U13: =IF($T13="","",IFERROR(VLOOKUP($T13,'Kunci dari RIASEC'!$A$4:$B$123,2,FALSE),"Rekomendasi belum tersedia")) | V13: =IF('entri hasil dari isian siswa'!B13="","",'entri hasil dari isian siswa'!HY13) -> Lengkapi 12 Self Estimate | W13: =IF($B13="","",SUM('entri hasil dari isian siswa'!E13:O13)) -> 4 | X13: =IF($B13="","",SUM('entri hasil dari isian siswa'!P13:Z13)) -> 0 | Y13: =IF($B13="","",SUM('entri hasil dari isian siswa'!AA13:AK13)) -> 0 | Z13: =IF($B13="","",SUM('entri hasil dari isian siswa'!AL13:AV13)) -> 0 | AA13: =IF($B13="","",SUM('entri hasil dari isian siswa'!AW13:BG13)) -> 0 | AB13: =IF($B13="","",SUM('entri hasil dari isian siswa'!BH13:BR13)) -> 0 | AC13: =IF($B13="","",SUM('entri hasil dari isian siswa'!BS13:CC13)) -> 0 | AD13: =IF($B13="","",SUM('entri hasil dari isian siswa'!CD13:CN13)) -> 0 | AE13: =IF($B13="","",SUM('entri hasil dari isian siswa'!CO13:CY13)) -> 0 | AF13: =IF($B13="","",SUM('entri hasil dari isian siswa'!CZ13:DJ13)) -> 0 | AG13: =IF($B13="","",SUM('entri hasil dari isian siswa'!DK13:DU13)) -> 0 | AH13: =IF($B13="","",SUM('entri hasil dari isian siswa'!DV13:EF13)) -> 0 | AI13: =IF($B13="","",SUM('entri hasil dari isian siswa'!EG13:ET13)) -> 0 | AJ13: =IF($B13="","",SUM('entri hasil dari isian siswa'!EU13:FH13)) -> 0 | AK13: =IF($B13="","",SUM('entri hasil dari isian siswa'!FI13:FV13)) -> 0 | AL13: =IF($B13="","",SUM('entri hasil dari isian siswa'!FW13:GJ13)) -> 0 | AM13: =IF($B13="","",SUM('entri hasil dari isian siswa'!GK13:GX13)) -> 0 | AN13: =IF($B13="","",SUM('entri hasil dari isian siswa'!GY13:HL13)) -> 0 | AO13: =IF($B13="","",'entri hasil dari isian siswa'!HM13+'entri hasil dari isian siswa'!HS13) -> 0 | AP13: =IF($B13="","",'entri hasil dari isian siswa'!HN13+'entri hasil dari isian siswa'!HT13) -> 0 | AQ13: =IF($B13="","",'entri hasil dari isian siswa'!HO13+'entri hasil dari isian siswa'!HU13) -> 0 | AR13: =IF($B13="","",'entri hasil dari isian siswa'!HP13+'entri hasil dari isian siswa'!HV13) -> 0 | AS13: =IF($B13="","",'entri hasil dari isian siswa'!HQ13+'entri hasil dari isian siswa'!HW13) -> 0 | AT13: =IF($B13="","",'entri hasil dari isian siswa'!HR13+'entri hasil dari isian siswa'!HX13) -> 0 | AU13: =IF($T13="","",LEFT($T13,2)) | AV13: =IF($AU13="","",IFERROR(VLOOKUP($AU13,'Kunci dari RIASEC'!$J$4:$K$33,2,FALSE),""))
A14: =ROW()-4 -> 10 | B14: =IF('entri hasil dari isian siswa'!B14="","",'entri hasil dari isian siswa'!B14) -> 22010 | C14: =IF('entri hasil dari isian siswa'!C14="","",'entri hasil dari isian siswa'!C14) -> Kukuh Priyatin | D14: =IF('entri hasil dari isian siswa'!D14="","",'entri hasil dari isian siswa'!D14) -> L | E14: =IF($B14="","",W14+AC14+AI14+AO14) -> 4 | F14: =IF($B14="","",X14+AD14+AJ14+AP14) -> 0 | G14: =IF($B14="","",Y14+AE14+AK14+AQ14) -> 0 | H14: =IF($B14="","",Z14+AF14+AL14+AR14) -> 0 | I14: =IF($B14="","",AA14+AG14+AM14+AS14) -> 0 | J14: =IF($B14="","",AB14+AH14+AN14+AT14) -> 0 | K14: =IF($V14<>"OK","",RANK(E14,$E14:$J14,0)+COUNTIF($E14:E14,E14)-1) | L14: =IF($V14<>"OK","",RANK(F14,$E14:$J14,0)+COUNTIF($E14:F14,F14)-1) | M14: =IF($V14<>"OK","",RANK(G14,$E14:$J14,0)+COUNTIF($E14:G14,G14)-1) | N14: =IF($V14<>"OK","",RANK(H14,$E14:$J14,0)+COUNTIF($E14:H14,H14)-1) | O14: =IF($V14<>"OK","",RANK(I14,$E14:$J14,0)+COUNTIF($E14:I14,I14)-1) | P14: =IF($V14<>"OK","",RANK(J14,$E14:$J14,0)+COUNTIF($E14:J14,J14)-1) | Q14: =IF($V14<>"OK","",INDEX($E$4:$J$4,1,MATCH(1,$K14:$P14,0))) | R14: =IF($V14<>"OK","",INDEX($E$4:$J$4,1,MATCH(2,$K14:$P14,0))) | S14: =IF($V14<>"OK","",INDEX($E$4:$J$4,1,MATCH(3,$K14:$P14,0))) | T14: =IF($V14<>"OK","",Q14&R14&S14) | U14: =IF($T14="","",IFERROR(VLOOKUP($T14,'Kunci dari RIASEC'!$A$4:$B$123,2,FALSE),"Rekomendasi belum tersedia")) | V14: =IF('entri hasil dari isian siswa'!B14="","",'entri hasil dari isian siswa'!HY14) -> Lengkapi 12 Self Estimate | W14: =IF($B14="","",SUM('entri hasil dari isian siswa'!E14:O14)) -> 4 | X14: =IF($B14="","",SUM('entri hasil dari isian siswa'!P14:Z14)) -> 0 | Y14: =IF($B14="","",SUM('entri hasil dari isian siswa'!AA14:AK14)) -> 0 | Z14: =IF($B14="","",SUM('entri hasil dari isian siswa'!AL14:AV14)) -> 0 | AA14: =IF($B14="","",SUM('entri hasil dari isian siswa'!AW14:BG14)) -> 0 | AB14: =IF($B14="","",SUM('entri hasil dari isian siswa'!BH14:BR14)) -> 0 | AC14: =IF($B14="","",SUM('entri hasil dari isian siswa'!BS14:CC14)) -> 0 | AD14: =IF($B14="","",SUM('entri hasil dari isian siswa'!CD14:CN14)) -> 0 | AE14: =IF($B14="","",SUM('entri hasil dari isian siswa'!CO14:CY14)) -> 0 | AF14: =IF($B14="","",SUM('entri hasil dari isian siswa'!CZ14:DJ14)) -> 0 | AG14: =IF($B14="","",SUM('entri hasil dari isian siswa'!DK14:DU14)) -> 0 | AH14: =IF($B14="","",SUM('entri hasil dari isian siswa'!DV14:EF14)) -> 0 | AI14: =IF($B14="","",SUM('entri hasil dari isian siswa'!EG14:ET14)) -> 0 | AJ14: =IF($B14="","",SUM('entri hasil dari isian siswa'!EU14:FH14)) -> 0 | AK14: =IF($B14="","",SUM('entri hasil dari isian siswa'!FI14:FV14)) -> 0 | AL14: =IF($B14="","",SUM('entri hasil dari isian siswa'!FW14:GJ14)) -> 0 | AM14: =IF($B14="","",SUM('entri hasil dari isian siswa'!GK14:GX14)) -> 0 | AN14: =IF($B14="","",SUM('entri hasil dari isian siswa'!GY14:HL14)) -> 0 | AO14: =IF($B14="","",'entri hasil dari isian siswa'!HM14+'entri hasil dari isian siswa'!HS14) -> 0 | AP14: =IF($B14="","",'entri hasil dari isian siswa'!HN14+'entri hasil dari isian siswa'!HT14) -> 0 | AQ14: =IF($B14="","",'entri hasil dari isian siswa'!HO14+'entri hasil dari isian siswa'!HU14) -> 0 | AR14: =IF($B14="","",'entri hasil dari isian siswa'!HP14+'entri hasil dari isian siswa'!HV14) -> 0 | AS14: =IF($B14="","",'entri hasil dari isian siswa'!HQ14+'entri hasil dari isian siswa'!HW14) -> 0 | AT14: =IF($B14="","",'entri hasil dari isian siswa'!HR14+'entri hasil dari isian siswa'!HX14) -> 0 | AU14: =IF($T14="","",LEFT($T14,2)) | AV14: =IF($AU14="","",IFERROR(VLOOKUP($AU14,'Kunci dari RIASEC'!$J$4:$K$33,2,FALSE),""))
A15: =ROW()-4 -> 11 | B15: =IF('entri hasil dari isian siswa'!B15="","",'entri hasil dari isian siswa'!B15) -> 22011 | C15: =IF('entri hasil dari isian siswa'!C15="","",'entri hasil dari isian siswa'!C15) -> Mas Karebet Setiawan | D15: =IF('entri hasil dari isian siswa'!D15="","",'entri hasil dari isian siswa'!D15) -> L | E15: =IF($B15="","",W15+AC15+AI15+AO15) -> 4 | F15: =IF($B15="","",X15+AD15+AJ15+AP15) -> 0 | G15: =IF($B15="","",Y15+AE15+AK15+AQ15) -> 0 | H15: =IF($B15="","",Z15+AF15+AL15+AR15) -> 0 | I15: =IF($B15="","",AA15+AG15+AM15+AS15) -> 0 | J15: =IF($B15="","",AB15+AH15+AN15+AT15) -> 0 | K15: =IF($V15<>"OK","",RANK(E15,$E15:$J15,0)+COUNTIF($E15:E15,E15)-1) | L15: =IF($V15<>"OK","",RANK(F15,$E15:$J15,0)+COUNTIF($E15:F15,F15)-1) | M15: =IF($V15<>"OK","",RANK(G15,$E15:$J15,0)+COUNTIF($E15:G15,G15)-1) | N15: =IF($V15<>"OK","",RANK(H15,$E15:$J15,0)+COUNTIF($E15:H15,H15)-1) | O15: =IF($V15<>"OK","",RANK(I15,$E15:$J15,0)+COUNTIF($E15:I15,I15)-1) | P15: =IF($V15<>"OK","",RANK(J15,$E15:$J15,0)+COUNTIF($E15:J15,J15)-1) | Q15: =IF($V15<>"OK","",INDEX($E$4:$J$4,1,MATCH(1,$K15:$P15,0))) | R15: =IF($V15<>"OK","",INDEX($E$4:$J$4,1,MATCH(2,$K15:$P15,0))) | S15: =IF($V15<>"OK","",INDEX($E$4:$J$4,1,MATCH(3,$K15:$P15,0))) | T15: =IF($V15<>"OK","",Q15&R15&S15) | U15: =IF($T15="","",IFERROR(VLOOKUP($T15,'Kunci dari RIASEC'!$A$4:$B$123,2,FALSE),"Rekomendasi belum tersedia")) | V15: =IF('entri hasil dari isian siswa'!B15="","",'entri hasil dari isian siswa'!HY15) -> Lengkapi 12 Self Estimate | W15: =IF($B15="","",SUM('entri hasil dari isian siswa'!E15:O15)) -> 4 | X15: =IF($B15="","",SUM('entri hasil dari isian siswa'!P15:Z15)) -> 0 | Y15: =IF($B15="","",SUM('entri hasil dari isian siswa'!AA15:AK15)) -> 0 | Z15: =IF($B15="","",SUM('entri hasil dari isian siswa'!AL15:AV15)) -> 0 | AA15: =IF($B15="","",SUM('entri hasil dari isian siswa'!AW15:BG15)) -> 0 | AB15: =IF($B15="","",SUM('entri hasil dari isian siswa'!BH15:BR15)) -> 0 | AC15: =IF($B15="","",SUM('entri hasil dari isian siswa'!BS15:CC15)) -> 0 | AD15: =IF($B15="","",SUM('entri hasil dari isian siswa'!CD15:CN15)) -> 0 | AE15: =IF($B15="","",SUM('entri hasil dari isian siswa'!CO15:CY15)) -> 0 | AF15: =IF($B15="","",SUM('entri hasil dari isian siswa'!CZ15:DJ15)) -> 0 | AG15: =IF($B15="","",SUM('entri hasil dari isian siswa'!DK15:DU15)) -> 0 | AH15: =IF($B15="","",SUM('entri hasil dari isian siswa'!DV15:EF15)) -> 0 | AI15: =IF($B15="","",SUM('entri hasil dari isian siswa'!EG15:ET15)) -> 0 | AJ15: =IF($B15="","",SUM('entri hasil dari isian siswa'!EU15:FH15)) -> 0 | AK15: =IF($B15="","",SUM('entri hasil dari isian siswa'!FI15:FV15)) -> 0 | AL15: =IF($B15="","",SUM('entri hasil dari isian siswa'!FW15:GJ15)) -> 0 | AM15: =IF($B15="","",SUM('entri hasil dari isian siswa'!GK15:GX15)) -> 0 | AN15: =IF($B15="","",SUM('entri hasil dari isian siswa'!GY15:HL15)) -> 0 | AO15: =IF($B15="","",'entri hasil dari isian siswa'!HM15+'entri hasil dari isian siswa'!HS15) -> 0 | AP15: =IF($B15="","",'entri hasil dari isian siswa'!HN15+'entri hasil dari isian siswa'!HT15) -> 0 | AQ15: =IF($B15="","",'entri hasil dari isian siswa'!HO15+'entri hasil dari isian siswa'!HU15) -> 0 | AR15: =IF($B15="","",'entri hasil dari isian siswa'!HP15+'entri hasil dari isian siswa'!HV15) -> 0 | AS15: =IF($B15="","",'entri hasil dari isian siswa'!HQ15+'entri hasil dari isian siswa'!HW15) -> 0 | AT15: =IF($B15="","",'entri hasil dari isian siswa'!HR15+'entri hasil dari isian siswa'!HX15) -> 0 | AU15: =IF($T15="","",LEFT($T15,2)) | AV15: =IF($AU15="","",IFERROR(VLOOKUP($AU15,'Kunci dari RIASEC'!$J$4:$K$33,2,FALSE),""))
A16: =ROW()-4 -> 12 | B16: =IF('entri hasil dari isian siswa'!B16="","",'entri hasil dari isian siswa'!B16) -> 22012 | C16: =IF('entri hasil dari isian siswa'!C16="","",'entri hasil dari isian siswa'!C16) -> Mauidhotul Hasanah Ismail | D16: =IF('entri hasil dari isian siswa'!D16="","",'entri hasil dari isian siswa'!D16) -> L | E16: =IF($B16="","",W16+AC16+AI16+AO16) -> 4 | F16: =IF($B16="","",X16+AD16+AJ16+AP16) -> 0 | G16: =IF($B16="","",Y16+AE16+AK16+AQ16) -> 0 | H16: =IF($B16="","",Z16+AF16+AL16+AR16) -> 0 | I16: =IF($B16="","",AA16+AG16+AM16+AS16) -> 0 | J16: =IF($B16="","",AB16+AH16+AN16+AT16) -> 0 | K16: =IF($V16<>"OK","",RANK(E16,$E16:$J16,0)+COUNTIF($E16:E16,E16)-1) | L16: =IF($V16<>"OK","",RANK(F16,$E16:$J16,0)+COUNTIF($E16:F16,F16)-1) | M16: =IF($V16<>"OK","",RANK(G16,$E16:$J16,0)+COUNTIF($E16:G16,G16)-1) | N16: =IF($V16<>"OK","",RANK(H16,$E16:$J16,0)+COUNTIF($E16:H16,H16)-1) | O16: =IF($V16<>"OK","",RANK(I16,$E16:$J16,0)+COUNTIF($E16:I16,I16)-1) | P16: =IF($V16<>"OK","",RANK(J16,$E16:$J16,0)+COUNTIF($E16:J16,J16)-1) | Q16: =IF($V16<>"OK","",INDEX($E$4:$J$4,1,MATCH(1,$K16:$P16,0))) | R16: =IF($V16<>"OK","",INDEX($E$4:$J$4,1,MATCH(2,$K16:$P16,0))) | S16: =IF($V16<>"OK","",INDEX($E$4:$J$4,1,MATCH(3,$K16:$P16,0))) | T16: =IF($V16<>"OK","",Q16&R16&S16) | U16: =IF($T16="","",IFERROR(VLOOKUP($T16,'Kunci dari RIASEC'!$A$4:$B$123,2,FALSE),"Rekomendasi belum tersedia")) | V16: =IF('entri hasil dari isian siswa'!B16="","",'entri hasil dari isian siswa'!HY16) -> Lengkapi 12 Self Estimate | W16: =IF($B16="","",SUM('entri hasil dari isian siswa'!E16:O16)) -> 4 | X16: =IF($B16="","",SUM('entri hasil dari isian siswa'!P16:Z16)) -> 0 | Y16: =IF($B16="","",SUM('entri hasil dari isian siswa'!AA16:AK16)) -> 0 | Z16: =IF($B16="","",SUM('entri hasil dari isian siswa'!AL16:AV16)) -> 0 | AA16: =IF($B16="","",SUM('entri hasil dari isian siswa'!AW16:BG16)) -> 0 | AB16: =IF($B16="","",SUM('entri hasil dari isian siswa'!BH16:BR16)) -> 0 | AC16: =IF($B16="","",SUM('entri hasil dari isian siswa'!BS16:CC16)) -> 0 | AD16: =IF($B16="","",SUM('entri hasil dari isian siswa'!CD16:CN16)) -> 0 | AE16: =IF($B16="","",SUM('entri hasil dari isian siswa'!CO16:CY16)) -> 0 | AF16: =IF($B16="","",SUM('entri hasil dari isian siswa'!CZ16:DJ16)) -> 0 | AG16: =IF($B16="","",SUM('entri hasil dari isian siswa'!DK16:DU16)) -> 0 | AH16: =IF($B16="","",SUM('entri hasil dari isian siswa'!DV16:EF16)) -> 0 | AI16: =IF($B16="","",SUM('entri hasil dari isian siswa'!EG16:ET16)) -> 0 | AJ16: =IF($B16="","",SUM('entri hasil dari isian siswa'!EU16:FH16)) -> 0 | AK16: =IF($B16="","",SUM('entri hasil dari isian siswa'!FI16:FV16)) -> 0 | AL16: =IF($B16="","",SUM('entri hasil dari isian siswa'!FW16:GJ16)) -> 0 | AM16: =IF($B16="","",SUM('entri hasil dari isian siswa'!GK16:GX16)) -> 0 | AN16: =IF($B16="","",SUM('entri hasil dari isian siswa'!GY16:HL16)) -> 0 | AO16: =IF($B16="","",'entri hasil dari isian siswa'!HM16+'entri hasil dari isian siswa'!HS16) -> 0 | AP16: =IF($B16="","",'entri hasil dari isian siswa'!HN16+'entri hasil dari isian siswa'!HT16) -> 0 | AQ16: =IF($B16="","",'entri hasil dari isian siswa'!HO16+'entri hasil dari isian siswa'!HU16) -> 0 | AR16: =IF($B16="","",'entri hasil dari isian siswa'!HP16+'entri hasil dari isian siswa'!HV16) -> 0 | AS16: =IF($B16="","",'entri hasil dari isian siswa'!HQ16+'entri hasil dari isian siswa'!HW16) -> 0 | AT16: =IF($B16="","",'entri hasil dari isian siswa'!HR16+'entri hasil dari isian siswa'!HX16) -> 0 | AU16: =IF($T16="","",LEFT($T16,2)) | AV16: =IF($AU16="","",IFERROR(VLOOKUP($AU16,'Kunci dari RIASEC'!$J$4:$K$33,2,FALSE),""))
... A204: =ROW()-4 -> 200 | B204: =IF('entri hasil dari isian siswa'!B204="","",'entri hasil dari isian siswa'!B204) | C204: =IF('entri hasil dari isian siswa'!C204="","",'entri hasil dari isian siswa'!C204) | D204: =IF('entri hasil dari isian siswa'!D204="","",'entri hasil dari isian siswa'!D204) | E204: =IF($B204="","",W204+AC204+AI204+AO204) | F204: =IF($B204="","",X204+AD204+AJ204+AP204) | G204: =IF($B204="","",Y204+AE204+AK204+AQ204) | H204: =IF($B204="","",Z204+AF204+AL204+AR204) | I204: =IF($B204="","",AA204+AG204+AM204+AS204) | J204: =IF($B204="","",AB204+AH204+AN204+AT204) | K204: =IF($V204<>"OK","",RANK(E204,$E204:$J204,0)+COUNTIF($E204:E204,E204)-1) | L204: =IF($V204<>"OK","",RANK(F204,$E204:$J204,0)+COUNTIF($E204:F204,F204)-1) | M204: =IF($V204<>"OK","",RANK(G204,$E204:$J204,0)+COUNTIF($E204:G204,G204)-1) | N204: =IF($V204<>"OK","",RANK(H204,$E204:$J204,0)+COUNTIF($E204:H204,H204)-1) | O204: =IF($V204<>"OK","",RANK(I204,$E204:$J204,0)+COUNTIF($E204:I204,I204)-1) | P204: =IF($V204<>"OK","",RANK(J204,$E204:$J204,0)+COUNTIF($E204:J204,J204)-1) | Q204: =IF($V204<>"OK","",INDEX($E$4:$J$4,1,MATCH(1,$K204:$P204,0))) | R204: =IF($V204<>"OK","",INDEX($E$4:$J$4,1,MATCH(2,$K204:$P204,0))) | S204: =IF($V204<>"OK","",INDEX($E$4:$J$4,1,MATCH(3,$K204:$P204,0))) | T204: =IF($V204<>"OK","",Q204&R204&S204) | U204: =IF($T204="","",IFERROR(VLOOKUP($T204,'Kunci dari RIASEC'!$A$4:$B$123,2,FALSE),"Rekomendasi belum tersedia")) | V204: =IF('entri hasil dari isian siswa'!B204="","",'entri hasil dari isian siswa'!HY204) | W204: =IF($B204="","",SUM('entri hasil dari isian siswa'!E204:O204)) | X204: =IF($B204="","",SUM('entri hasil dari isian siswa'!P204:Z204)) | Y204: =IF($B204="","",SUM('entri hasil dari isian siswa'!AA204:AK204)) | Z204: =IF($B204="","",SUM('entri hasil dari isian siswa'!AL204:AV204)) | AA204: =IF($B204="","",SUM('entri hasil dari isian siswa'!AW204:BG204)) | AB204: =IF($B204="","",SUM('entri hasil dari isian siswa'!BH204:BR204)) | AC204: =IF($B204="","",SUM('entri hasil dari isian siswa'!BS204:CC204)) | AD204: =IF($B204="","",SUM('entri hasil dari isian siswa'!CD204:CN204)) | AE204: =IF($B204="","",SUM('entri hasil dari isian siswa'!CO204:CY204)) | AF204: =IF($B204="","",SUM('entri hasil dari isian siswa'!CZ204:DJ204)) | AG204: =IF($B204="","",SUM('entri hasil dari isian siswa'!DK204:DU204)) | AH204: =IF($B204="","",SUM('entri hasil dari isian siswa'!DV204:EF204)) | AI204: =IF($B204="","",SUM('entri hasil dari isian siswa'!EG204:ET204)) | AJ204: =IF($B204="","",SUM('entri hasil dari isian siswa'!EU204:FH204)) | AK204: =IF($B204="","",SUM('entri hasil dari isian siswa'!FI204:FV204)) | AL204: =IF($B204="","",SUM('entri hasil dari isian siswa'!FW204:GJ204)) | AM204: =IF($B204="","",SUM('entri hasil dari isian siswa'!GK204:GX204)) | AN204: =IF($B204="","",SUM('entri hasil dari isian siswa'!GY204:HL204)) | AO204: =IF($B204="","",'entri hasil dari isian siswa'!HM204+'entri hasil dari isian siswa'!HS204) | AP204: =IF($B204="","",'entri hasil dari isian siswa'!HN204+'entri hasil dari isian siswa'!HT204) | AQ204: =IF($B204="","",'entri hasil dari isian siswa'!HO204+'entri hasil dari isian siswa'!HU204) | AR204: =IF($B204="","",'entri hasil dari isian siswa'!HP204+'entri hasil dari isian siswa'!HV204) | AS204: =IF($B204="","",'entri hasil dari isian siswa'!HQ204+'entri hasil dari isian siswa'!HW204) | AT204: =IF($B204="","",'entri hasil dari isian siswa'!HR204+'entri hasil dari isian siswa'!HX204) | AU204: =IF($T204="","",LEFT($T204,2)) | AV204: =IF($AU204="","",IFERROR(VLOOKUP($AU204,'Kunci dari RIASEC'!$J$4:$K$33,2,FALSE),""))

Sheet Kunci dari RIASEC
A1: KUNCI RIASEC — 120 KODE + REKOMENDASI PEKERJAAN MODERN | J1: TINGKAT KONSISTENSI DUA HURUF DOMINAN
A2: Daftar pekerjaan diperbarui dengan istilah pekerjaan yang masih relevan saat ini. Rekomendasi merupakan contoh bidang/peran yang selaras dengan pola RIASEC, bukan daftar profesi yang bersifat eksklusif. | E2: Rujukan pemutakhiran: O*NET OnLine Career Interest Types / O*NET Database 31.0 (Agustus 2026). | J2: Dasar | K2: Tinggi = berdampingan pada heksagon R-I-A-S-E-C; Sedang = selang satu; Rendah = berlawanan.
A3: Kode RIASEC | B3: Rekomendasi Pekerjaan Modern | C3: Fokus Kombinasi | D3: Sumber Rujukan | E3: Tipe | F3: Nama | G3: Ringkasan Karakteristik Modern | H3: Jurusan / Bidang Studi Relevan | J3: Pasangan Dominan | K3: Tingkat Konsistensi
A4: RIA | B4: Engineer mekatronika; Teknisi instrumentasi dan kontrol; Teknisi peralatan biomedis; Spesialis pengujian non-destruktif (NDT); Teknolog survei dan pemetaan; Desainer prototipe teknis; Spesialis CAD pengembangan produk; Technical visualization specialist; Engineer robotika/robotics engineer; Engineer sistem energi terbarukan; Architect; Teknisi sistem drone/UAS; Engineer perangkat biomedis | C4: Realistic > Investigative > Artistic | D4: https://www.onetonline.org/explore/interests/ | E4: R | F4: Realistic | G4: Menyukai aktivitas praktis dan langsung, bekerja dengan alat, mesin, teknologi, material, hewan, atau lingkungan fisik. Cenderung nyaman dengan pemecahan masalah konkret, aktivitas lapangan, dan hasil kerja yang dapat diamati. | H4: Teknik Mesin, Teknik Elektro, Teknik Sipil, Mekatronika, Teknik Otomotif, Teknik Energi/Energi Terbarukan, Geomatika, Pertanian, Perikanan, Kehutanan, Teknik Industri. | J4: AC | K4: Rendah
A5: RIS | B5: Engineer mekatronika; Teknisi instrumentasi dan kontrol; Teknisi peralatan biomedis; Spesialis pengujian non-destruktif (NDT); Teknolog survei dan pemetaan; Teknisi layanan peralatan medis; Spesialis teknologi rehabilitasi; Instruktur teknis lapangan; Engineer robotika/robotics engineer; Engineer sistem energi terbarukan; Forester / forestry technician; Teknisi sistem drone/UAS; Engineer perangkat biomedis | C5: Realistic > Investigative > Social | D5: https://www.onetonline.org/explore/interests/ | E5: I | F5: Investigative | G5: Menyukai kegiatan analitis, penelitian, eksplorasi konsep dan data, serta pemecahan masalah kompleks. Cenderung tertarik memahami bagaimana sesuatu bekerja melalui observasi, penalaran, eksperimen, penelitian, atau pemodelan. | H5: Sains Data, Statistika, Matematika, Ilmu Komputer, Keamanan Siber, Bioinformatika, Biologi, Kimia, Fisika, Geologi, Kedokteran, Farmasi, Kesehatan Masyarakat. | J5: AE | K5: Sedang
A6: RIE | B6: Engineer mekatronika; Teknisi instrumentasi dan kontrol; Teknisi peralatan biomedis; Spesialis pengujian non-destruktif (NDT); Teknolog survei dan pemetaan; Technical sales engineer; Koordinator proyek teknik; Supervisor pemeliharaan teknis; Engineer robotika/robotics engineer; Engineer sistem energi terbarukan; Teknisi sistem drone/UAS; Engineer perangkat biomedis | C6: Realistic > Investigative > Enterprising | D6: https://www.onetonline.org/explore/interests/ | E6: A | F6: Artistic | G6: Menyukai ekspresi kreatif, penciptaan ide, desain, bahasa, musik, seni pertunjukan, media, dan karya visual. Cenderung menghargai kebebasan berekspresi dan pekerjaan yang memberi ruang bagi kreativitas serta orisinalitas. | H6: Desain Komunikasi Visual, Desain Produk, Desain Interior, Arsitektur, Seni Rupa, Animasi, Film, Musik, Sastra, Fotografi, Desain Gim, Media Digital, Teknologi Kreatif. | J6: AI | K6: Tinggi
A7: RIC | B7: Engineer mekatronika; Teknisi instrumentasi dan kontrol; Teknisi peralatan biomedis; Spesialis pengujian non-destruktif (NDT); Teknolog survei dan pemetaan; Teknisi kalibrasi; Quality control technician; Reliability/maintenance analyst; Engineer robotika/robotics engineer; Engineer sistem energi terbarukan; Dental laboratory technician; Industrial engineer; Automotive engineer / EV engineer; Automotive technician / EV technician; Telecommunications technician | C7: Realistic > Investigative > Conventional | D7: https://www.onetonline.org/explore/interests/ | E7: S | F7: Social | G7: Menyukai aktivitas membantu, mengajar, membimbing, merawat, mendampingi, berkomunikasi, dan bekerja bersama orang lain. Cenderung memperoleh kepuasan dari perkembangan, pembelajaran, kesehatan, dan kesejahteraan individu atau komunitas. | H7: Pendidikan, Bimbingan dan Konseling, Psikologi, Keperawatan, Kesehatan Masyarakat, Pekerjaan Sosial, Pendidikan Khusus, Terapi/Rehabilitasi, Pengembangan Masyarakat, Pengembangan SDM, Sosiologi. | J7: AR | K7: Sedang
A8: RAI | B8: Desainer produk industri; Drafter/BIM modeler; Desainer furnitur; Teknisi prototipe dan maker; Teknisi fabrikasi pameran/set; R&D prototype designer; Desainer produk berbasis riset pengguna; Spesialis material dan prototyping; Spesialis fabrikasi digital/additive manufacturing; Desainer prototipe produk; Teknisi pencetakan 3D; Spesialis produksi pameran dan instalasi kreatif | C8: Realistic > Artistic > Investigative | D8: https://www.onetonline.org/explore/interests/ | E8: E | F8: Enterprising | G8: Menyukai aktivitas memimpin, memengaruhi, meyakinkan, bernegosiasi, mengembangkan peluang, mengorganisasi kegiatan, menjalankan usaha atau proyek, dan mencapai target. Cenderung tertarik pada kepemimpinan, bisnis, kewirausahaan, pemasaran, dan pengambilan keputusan. | H8: Manajemen, Kewirausahaan, Administrasi Bisnis, Pemasaran, Manajemen Produk, Hubungan Masyarakat, Manajemen Penjualan, Hukum, Keuangan, Bisnis Digital, Manajemen Perhotelan, Bisnis Internasional. | J8: AS | K8: Tinggi
A9: RAS | B9: Desainer produk industri; Drafter/BIM modeler; Desainer furnitur; Teknisi prototipe dan maker; Teknisi fabrikasi pameran/set; Desainer produk asistif; Instruktur keterampilan desain/fabrikasi; Desainer ruang pembelajaran; Spesialis fabrikasi digital/additive manufacturing; Desainer prototipe produk; Teknisi pencetakan 3D; Spesialis produksi pameran dan instalasi kreatif | C9: Realistic > Artistic > Social | D9: https://www.onetonline.org/explore/interests/ | E9: C | F9: Conventional | G9: Menyukai aktivitas yang terstruktur, teratur, teliti, sistematis, dan berbasis prosedur, data, angka, dokumen, serta pengelolaan informasi. Cenderung nyaman dengan aturan yang jelas, ketepatan, pencatatan, dan standar kerja yang konsisten. | H9: Akuntansi, Perpajakan, Keuangan, Administrasi Bisnis, Administrasi Perkantoran, Sistem Informasi, Manajemen Data, Audit, Perbankan, Manajemen Rantai Pasok, Manajemen Operasi, Kearsipan dan Manajemen Dokumen. | J9: CA | K9: Rendah
A10: RAE | B10: Desainer produk industri; Drafter/BIM modeler; Desainer furnitur; Teknisi prototipe dan maker; Teknisi fabrikasi pameran/set; Koordinator produksi kreatif; Supervisor workshop desain; Product development coordinator; Spesialis fabrikasi digital/additive manufacturing; Desainer prototipe produk; Teknisi pencetakan 3D; Spesialis produksi pameran dan instalasi kreatif | C10: Realistic > Artistic > Enterprising | D10: https://www.onetonline.org/explore/interests/ | J10: CE | K10: Tinggi
A11: RAC | B11: Desainer produk industri; Drafter/BIM modeler; Desainer furnitur; Teknisi prototipe dan maker; Teknisi fabrikasi pameran/set; Technical illustrator/drafter; Koordinator dokumentasi desain; Spesialis standardisasi gambar teknik; Spesialis fabrikasi digital/additive manufacturing; Desainer prototipe produk; Floral designer; Woodworker / furniture maker; Architectural drafter / BIM technician; Carpenter; Teknisi pencetakan 3D | C11: Realistic > Artistic > Conventional | D11: https://www.onetonline.org/explore/interests/ | J11: CI | K11: Sedang
A12: RSI | B12: Paramedis lapangan; Asisten fisioterapi; Asisten terapi okupasi; Teknisi veteriner/perawat hewan; Instruktur kebugaran dan aktivitas fisik; Teknisi rehabilitasi medis; Asisten laboratorium klinis lapangan; Teknisi peralatan terapi; Teknisi teknologi rehabilitasi; Emergency Medical Technician (EMT); Spesialis peralatan adaptif; Instruktur aktivitas luar ruang | C12: Realistic > Social > Investigative | D12: https://www.onetonline.org/explore/interests/ | J12: CR | K12: Tinggi
A13: RSA | B13: Paramedis lapangan; Asisten fisioterapi; Asisten terapi okupasi; Teknisi veteriner/perawat hewan; Instruktur kebugaran dan aktivitas fisik; Instruktur aktivitas rekreatif; Fasilitator terapi berbasis aktivitas; Pelatih gerak/aktivitas kreatif; Teknisi teknologi rehabilitasi; Emergency Medical Technician (EMT); Spesialis peralatan adaptif; Instruktur aktivitas luar ruang | C13: Realistic > Social > Artistic | D13: https://www.onetonline.org/explore/interests/ | J13: CS | K13: Sedang
A14: RSE | B14: Paramedis lapangan; Asisten fisioterapi; Asisten terapi okupasi; Teknisi veteriner/perawat hewan; Instruktur kebugaran dan aktivitas fisik; Koordinator layanan lapangan; Supervisor pusat kebugaran; Koordinator operasi klinik rehabilitasi; Teknisi teknologi rehabilitasi; Emergency Medical Technician (EMT); Baker; Cook / chef; Spesialis peralatan adaptif; Instruktur aktivitas luar ruang | C14: Realistic > Social > Enterprising | D14: https://www.onetonline.org/explore/interests/ | J14: EA | K14: Sedang
A15: RSC | B15: Paramedis lapangan; Asisten fisioterapi; Asisten terapi okupasi; Teknisi veteriner/perawat hewan; Instruktur kebugaran dan aktivitas fisik; Koordinator alat dan logistik medis; Teknisi sterilisasi dan persiapan alat; Petugas dokumentasi layanan lapangan; Teknisi teknologi rehabilitasi; Emergency Medical Technician (EMT); Spesialis peralatan adaptif; Instruktur aktivitas luar ruang | C15: Realistic > Social > Conventional | D15: https://www.onetonline.org/explore/interests/ | J15: EC | K15: Tinggi
A16: REI | B16: Supervisor konstruksi; Supervisor produksi; Manajer fasilitas; Supervisor operasi lapangan; Technical sales specialist; Technical project coordinator; Supervisor commissioning; Manajer proyek instalasi teknis; Manajer operasi fasilitas pintar; Supervisor operasi energi terbarukan; Field service manager | C16: Realistic > Enterprising > Investigative | D16: https://www.onetonline.org/explore/interests/ | J16: EI | K16: Rendah
A17: REA | B17: Supervisor konstruksi; Supervisor produksi; Manajer fasilitas; Supervisor operasi lapangan; Technical sales specialist; Manajer produksi pameran; Supervisor workshop kreatif; Koordinator proyek desain-konstruksi; Manajer operasi fasilitas pintar; Supervisor operasi energi terbarukan; Field service manager | C17: Realistic > Enterprising > Artistic | D17: https://www.onetonline.org/explore/interests/ | J17: ER | K17: Sedang
A18: RES | B18: Supervisor konstruksi; Supervisor produksi; Manajer fasilitas; Supervisor operasi lapangan; Technical sales specialist; Supervisor layanan teknis; Manajer operasi fasilitas publik; Koordinator keselamatan dan pelatihan lapangan; Manajer operasi fasilitas pintar; Supervisor operasi energi terbarukan; Firefighter; Correctional officer; Field service manager | C18: Realistic > Enterprising > Social | D18: https://www.onetonline.org/explore/interests/ | J18: ES | K18: Tinggi
A19: REC | B19: Supervisor konstruksi; Supervisor produksi; Manajer fasilitas; Supervisor operasi lapangan; Technical sales specialist; Manajer pemeliharaan; Supervisor perencanaan produksi; Koordinator supply chain teknis; Manajer operasi fasilitas pintar; Supervisor operasi energi terbarukan; Field service manager | C19: Realistic > Enterprising > Conventional | D19: https://www.onetonline.org/explore/interests/ | J19: IA | K19: Tinggi
A20: RCI | B20: Teknisi quality control; Programmer/operator CNC; Teknisi kalibrasi; Maintenance planner; Production planner; Quality assurance technician; Reliability analyst teknis; Teknisi pengujian dan inspeksi; Teknisi smart manufacturing; Maintenance planning specialist; Building inspector; Civil engineering technician; Surveyor / surveying technician; Marine engineer / ship engineer; Safety inspector | C20: Realistic > Conventional > Investigative | D20: https://www.onetonline.org/explore/interests/ | J20: IC | K20: Sedang
A21: RCA | B21: Teknisi quality control; Programmer/operator CNC; Teknisi kalibrasi; Maintenance planner; Production planner; CAD/CAM production specialist; Teknisi produksi prototipe; Spesialis finishing presisi; Teknisi smart manufacturing; Maintenance planning specialist; QA/QC technician; Koordinator otomasi gudang | C21: Realistic > Conventional > Artistic | D21: https://www.onetonline.org/explore/interests/ | J21: IE | K21: Rendah
... A33: ISA | B33: Epidemiolog; Psikolog klinis; Peneliti kesehatan masyarakat; Peneliti pendidikan; Ilmuwan gizi; Peneliti komunikasi kesehatan; Behavioral design researcher; Pengembang media edukasi berbasis riset; Health data scientist; Behavioral scientist; Physician / psychiatrist; Sociologist; Public health researcher; Clinical research coordinator | C33: Investigative > Social > Artistic | D33: https://www.onetonline.org/explore/interests/ | J33: SR | K33: Rendah
A34: ISE | B34: Epidemiolog; Psikolog klinis; Peneliti kesehatan masyarakat; Peneliti pendidikan; Ilmuwan gizi; Health program analyst; Research program manager; Policy research consultant; Health data scientist; Behavioral scientist; Public health researcher; Clinical research coordinator | C34: Investigative > Social > Enterprising | D34: https://www.onetonline.org/explore/interests/
A35: ISC | B35: Epidemiolog; Psikolog klinis; Peneliti kesehatan masyarakat; Peneliti pendidikan; Ilmuwan gizi; Clinical data analyst; Health informatics analyst; Research data manager; Health data scientist; Behavioral scientist; Public health researcher; Clinical research coordinator | C35: Investigative > Social > Conventional | D35: https://www.onetonline.org/explore/interests/ | J35: Catatan | K35: Pola CR ditambahkan pada kategori Tinggi agar seluruh 30 pasangan dua huruf unik terklasifikasi.
A36: IER | B36: Market research analyst; Operations research analyst; Product analyst; Strategy analyst; Business intelligence analyst; Industrial operations analyst; Technical market analyst; Supply chain analytics specialist; Product insights analyst; Innovation strategy analyst; R&D manager; Management consultant; Market intelligence analyst; AI product analyst | C36: Investigative > Enterprising > Realistic | D36: https://www.onetonline.org/explore/interests/ | J36: Sumber awal | K36: Tabel kode dan jabatan Holland pada PDF yang dilampirkan pengguna.
A37: IEA | B37: Market research analyst; Operations research analyst; Product analyst; Strategy analyst; Business intelligence analyst; Consumer insight strategist; Innovation concept researcher; Product experience analyst; Product insights analyst; Innovation strategy analyst; Market intelligence analyst; AI product analyst | C37: Investigative > Enterprising > Artistic | D37: https://www.onetonline.org/explore/interests/ | J37: Rujukan | K37: https://www.onetcenter.org/db_releases.html
A38: IES | B38: Market research analyst; Operations research analyst; Product analyst; Strategy analyst; Business intelligence analyst; People analytics specialist; Education program analyst; Customer research analyst; Product insights analyst; Innovation strategy analyst; Urban/regional planner; Market intelligence analyst; AI product analyst | C38: Investigative > Enterprising > Social | D38: https://www.onetonline.org/explore/interests/
A39: IEC | B39: Market research analyst; Operations research analyst; Product analyst; Strategy analyst; Business intelligence analyst; Business data analyst; Financial planning analyst; Decision-support analyst; Product insights analyst; Innovation strategy analyst; Systems analyst; Market intelligence analyst; AI product analyst | C39: Investigative > Enterprising > Conventional | D39: https://www.onetonline.org/explore/interests/
A40: ICR | B40: Data scientist; Statistikawan; Aktuaris; Analis keamanan siber; Risk analyst; Industrial data analyst; Quality data analyst; Cyber-physical systems analyst; Machine learning engineer / AI engineer; Cybersecurity analyst; Mathematician; Statistician; Detective / criminal investigator; Data governance analyst; Quantitative analyst | C40: Investigative > Conventional > Realistic | D40: https://www.onetonline.org/explore/interests/
A41: ICA | B41: Data scientist; Statistikawan; Aktuaris; Analis keamanan siber; Risk analyst; Data visualization analyst; Information design analyst; Digital experience analytics specialist; Machine learning engineer / AI engineer; Cybersecurity analyst; Data governance analyst; Quantitative analyst | C41: Investigative > Conventional > Artistic | D41: https://www.onetonline.org/explore/interests/
A42: ICS | B42: Data scientist; Statistikawan; Aktuaris; Analis keamanan siber; Risk analyst; Health data analyst; Education data analyst; People analytics specialist; Machine learning engineer / AI engineer; Cybersecurity analyst; Data governance analyst; Quantitative analyst | C42: Investigative > Conventional > Social | D42: https://www.onetonline.org/explore/interests/
A43: ICE | B43: Data scientist; Statistikawan; Aktuaris; Analis keamanan siber; Risk analyst; Business intelligence consultant; Risk strategy analyst; Pricing/revenue analyst; Machine learning engineer / AI engineer; Cybersecurity analyst; Data governance analyst; Quantitative analyst | C43: Investigative > Conventional > Enterprising | D43: https://www.onetonline.org/explore/interests/
A44: ARI | B44: Industrial designer; Product designer; Interior designer; Exhibition/set designer; 3D artist/modeler; Design researcher; Material/CMF designer; Product innovation designer; Creative technologist; Immersive media designer (AR/VR); Desainer interior; Industrial/Product Designer; 3D product visualizer; Digital fabrication designer | C44: Artistic > Realistic > Investigative | D44: https://www.onetonline.org/explore/interests/
A45: ARS | B45: Industrial designer; Product designer; Interior designer; Exhibition/set designer; 3D artist/modeler; Desainer produk inklusif; Community design facilitator; Desainer ruang edukatif; Creative technologist; Immersive media designer (AR/VR); 3D product visualizer; Digital fabrication designer | C45: Artistic > Realistic > Social | D45: https://www.onetonline.org/explore/interests/
A46: ARE | B46: Industrial designer; Product designer; Interior designer; Exhibition/set designer; 3D artist/modeler; Creative product lead; Design entrepreneur; Creative production manager; Creative technologist; Immersive media designer (AR/VR); Fotografer / visual content creator; Fashion designer; 3D product visualizer; Digital fabrication designer | C46: Artistic > Realistic > Enterprising | D46: https://www.onetonline.org/explore/interests/
A47: ARC | B47: Industrial designer; Product designer; Interior designer; Exhibition/set designer; 3D artist/modeler; Design production coordinator; Technical design documentation specialist; Digital fabrication planner; Creative technologist; Immersive media designer (AR/VR); 3D product visualizer; Digital fabrication designer | C47: Artistic > Realistic > Conventional | D47: https://www.onetonline.org/explore/interests/
A48: AIR | B48: UX/UI designer; Information visualization designer; Game designer; Interaction designer; Creative technologist; Interaction prototyping designer; XR/immersive experience designer; Digital fabrication designer; Generative-AI creative specialist; Pelukis / visual artist | C48: Artistic > Investigative > Realistic | D48: https://www.onetonline.org/explore/interests/
A49: AIS | B49: UX/UI designer; Information visualization designer; Game designer; Interaction designer; Creative technologist; Learning experience designer; Accessible UX designer; Service designer untuk layanan publik; Generative-AI creative specialist; Kurator museum | C49: Artistic > Investigative > Social | D49: https://www.onetonline.org/explore/interests/
... A123: CES | B123: Akuntan; Auditor; Procurement specialist; Business operations analyst; Banking operations specialist; Payroll and benefits administrator; Customer billing supervisor; School finance administrator; Finance operations analyst; Payroll specialist | C123: Conventional > Enterprising > Social | D123: https://www.onetonline.org/explore/interests/

Sheet Kunci Jawaban
A1: KUNCI PEMETAAN ITEM DAN PERNYATAAN HOLLAND RIASEC
A2: VERSI FINAL 2026 — 216 item tetap dipertahankan (36 item per tipe). Redaksi telah ditinjau ulang untuk mengurangi tumpang tindih konstruk antar-RIASEC tanpa mengubah nomor item, kelompok, atau kunci skornya.
A3: Item | B3: Kelompok | C3: Tipe RIASEC | D3: Aturan Skor | E3: Pernyataan
A4: 1 | B4: Aktivitas | C4: R | D4: 1 = dipilih/setuju; 0/kosong = tidak dipilih | E4: Saya suka memperbaiki atau merakit perangkat listrik/elektronik sederhana.
A5: 2 | B5: Aktivitas | C5: R | D5: 1 = dipilih/setuju; 0/kosong = tidak dipilih | E5: Saya suka memperbaiki alat mekanik atau kendaraan.
A6: 3 | B6: Aktivitas | C6: R | D6: 1 = dipilih/setuju; 0/kosong = tidak dipilih | E6: Saya suka membuat atau merakit benda dari kayu atau bahan lain.
A7: 4 | B7: Aktivitas | C7: R | D7: 1 = dipilih/setuju; 0/kosong = tidak dipilih | E7: Saya suka merakit peralatan mekanik atau perangkat teknis.
A8: 5 | B8: Aktivitas | C8: R | D8: 1 = dipilih/setuju; 0/kosong = tidak dipilih | E8: Saya suka mengoperasikan kendaraan, alat berat, atau mesin untuk kegiatan lapangan.
A9: 6 | B9: Aktivitas | C9: R | D9: 1 = dipilih/setuju; 0/kosong = tidak dipilih | E9: Saya suka menggunakan perkakas mesin, peralatan kerja logam, atau alat produksi.
A10: 7 | B10: Aktivitas | C10: R | D10: 1 = dipilih/setuju; 0/kosong = tidak dipilih | E10: Saya suka bekerja di bengkel, workshop, atau ruang praktik teknik.
A11: 8 | B11: Aktivitas | C11: R | D11: 1 = dipilih/setuju; 0/kosong = tidak dipilih | E11: Saya suka mempelajari keterampilan teknis dan pertukangan.
A12: 9 | B12: Aktivitas | C12: R | D12: 1 = dipilih/setuju; 0/kosong = tidak dipilih | E12: Saya suka mempelajari gambar teknik, CAD, atau rancangan konstruksi.
A13: 10 | B13: Aktivitas | C13: R | D13: 1 = dipilih/setuju; 0/kosong = tidak dipilih | E13: Saya suka mempelajari pembuatan dan perakitan benda dari kayu atau bahan lain.
A14: 11 | B14: Aktivitas | C14: R | D14: 1 = dipilih/setuju; 0/kosong = tidak dipilih | E14: Saya suka mempelajari cara merawat dan memperbaiki kendaraan atau mesin.
A15: 12 | B15: Aktivitas | C15: I | D15: 1 = dipilih/setuju; 0/kosong = tidak dipilih | E15: Saya suka membaca buku, artikel, atau konten ilmiah.
... A231: 228 | B231: Self Estimate - Keterampilan | C231: C | D231: Nilai 1–7 (wajib diisi; 1 = terendah, 7 = tertinggi) | E231: Nilai keterampilan diri Anda pada bidang terstruktur-administratif: data, keuangan, dokumen, prosedur, dan ketelitian.

Sheet Pertanyaan
A1: LEMBAR PERTANYAAN TES MINAT KARIR HOLLAND RIASEC — 216 ITEM — VERSI FINAL
A2: Petunjuk: baca setiap pernyataan dan pilih 1 jika sesuai dengan minat/kondisi Anda, atau 0 jika tidak. Tidak ada jawaban benar atau salah. Jawablah sesuai diri Anda, bukan berdasarkan harapan orang lain.
A3: No. | B3: Bagian | C3: Pernyataan | D3: Jawaban (0/1)
A4: 1 | B4: Aktivitas | C4: Saya suka memperbaiki atau merakit perangkat listrik/elektronik sederhana.
A5: 2 | B5: Aktivitas | C5: Saya suka memperbaiki alat mekanik atau kendaraan.
A6: 3 | B6: Aktivitas | C6: Saya suka membuat atau merakit benda dari kayu atau bahan lain.
A7: 4 | B7: Aktivitas | C7: Saya suka merakit peralatan mekanik atau perangkat teknis.
A8: 5 | B8: Aktivitas | C8: Saya suka mengoperasikan kendaraan, alat berat, atau mesin untuk kegiatan lapangan.
A9: 6 | B9: Aktivitas | C9: Saya suka menggunakan perkakas mesin, peralatan kerja logam, atau alat produksi.
A10: 7 | B10: Aktivitas | C10: Saya suka bekerja di bengkel, workshop, atau ruang praktik teknik.
A11: 8 | B11: Aktivitas | C11: Saya suka mempelajari keterampilan teknis dan pertukangan.
A12: 9 | B12: Aktivitas | C12: Saya suka mempelajari gambar teknik, CAD, atau rancangan konstruksi.
A13: 10 | B13: Aktivitas | C13: Saya suka mempelajari pembuatan dan perakitan benda dari kayu atau bahan lain.
A14: 11 | B14: Aktivitas | C14: Saya suka mempelajari cara merawat dan memperbaiki kendaraan atau mesin.
A15: 12 | B15: Aktivitas | C15: Saya suka membaca buku, artikel, atau konten ilmiah.
... A219: 216 | B219: Pekerjaan | C219: Saya tertarik bekerja sebagai inventory / receiving specialist atau petugas penerimaan barang.
A221: SELF ESTIMATE — 12 PENILAIAN TAMBAHAN (BUKAN BAGIAN DARI 216 ITEM)
A222: Beri nilai 1–7 pada setiap bidang: 1 = sangat rendah, 7 = sangat tinggi. Enam baris pertama menilai pengetahuan diri; enam baris berikutnya menilai keterampilan diri.
A223: No. | B223: Aspek | C223: Bidang | D223: Nilai (1–7)
A224: 1 | B224: Pengetahuan | C224: Praktis–Teknis — praktis-teknis: alat, mesin, perangkat, konstruksi, atau pekerjaan lapangan
A225: 2 | B225: Pengetahuan | C225: Analitis–Ilmiah — analitis-ilmiah: penelitian, data, sains, logika, dan pemecahan masalah
A226: 3 | B226: Pengetahuan | C226: Kreatif–Artistik — kreatif-artistik: desain, visual, musik, media, bahasa, dan ekspresi kreatif
A227: 4 | B227: Pengetahuan | C227: Sosial–Membantu — sosial: membantu, mengajar, membimbing, merawat, dan berkomunikasi
A228: 5 | B228: Pengetahuan | C228: Kepemimpinan–Bisnis — kepemimpinan-bisnis: memimpin, bernegosiasi, menjual, dan mengembangkan peluang
A229: 6 | B229: Pengetahuan | C229: Terstruktur–Administratif — terstruktur-administratif: data, keuangan, dokumen, prosedur, dan ketelitian
A230: 7 | B230: Keterampilan | C230: Praktis–Teknis — praktis-teknis: alat, mesin, perangkat, konstruksi, atau pekerjaan lapangan
A231: 8 | B231: Keterampilan | C231: Analitis–Ilmiah — analitis-ilmiah: penelitian, data, sains, logika, dan pemecahan masalah
A232: 9 | B232: Keterampilan | C232: Kreatif–Artistik — kreatif-artistik: desain, visual, musik, media, bahasa, dan ekspresi kreatif
A233: 10 | B233: Keterampilan | C233: Sosial–Membantu — sosial: membantu, mengajar, membimbing, merawat, dan berkomunikasi
A234: 11 | B234: Keterampilan | C234: Kepemimpinan–Bisnis — kepemimpinan-bisnis: memimpin, bernegosiasi, menjual, dan mengembangkan peluang
A235: 12 | B235: Keterampilan | C235: Terstruktur–Administratif — terstruktur-administratif: data, keuangan, dokumen, prosedur, dan ketelitian
